{"time":"2014-12-26 00:00:00 -0800","subject":"内耳再生医療・遺伝子治療の研究員募集","period":"2014-12-26:2015-01-25:決定次第終了致します","place":["東京都"],"place_en":["Tokyo"],"genre":"医歯薬学:医歯薬学:生物学","institution":"順天堂大学","title":"研究員・ポスドク相当","id":"D114121427","data":{"データ番号":"D114121427","公開開始日":"2014年12月26日","更新日":"2014年12月26日","求人件名":"内耳再生医療・遺伝子治療の研究員募集","機関名":"順天堂大学","機関または部署":"http://www.juntendojibi.com/","部署名":"医学部耳鼻咽喉科学講座","機関種別":"私立大学","求人内容":"<div class=\"margin-01\"><p style=\"word-wrap: break-word;\">[機関の説明(募集の背景、機関の詳細、プロジェクトの説明等)]<br>iPS細胞等を用いた内耳再生医療の研究に関し研究員を募集します。難聴への細胞治療・遺伝子治療・創薬の研究開発です。<br>参考論文<br>Kamiya K, Proc Natl Acad Sci U S A. 2014, 111(25):9307-12.<br>Kamiya K, Journal of Clinical Investigation 2014;124(4):1598–1607.<br><br>[仕事内容(業務内容、担当科目等)]<br>分子生物学的実験（iPS細胞等の分化誘導、遺伝子治療実験、遺伝子改変マウスを用いた病態解析と治療法開発、創薬研究）および英文論文作成<br><br>[勤務地住所等]<br>順天堂大学医学部耳鼻咽喉科学講座　文京区本郷2-1-1<br>JR・地下鉄丸の内線　御茶ノ水駅より徒歩5分<br>（丸ノ内線　本郷三丁目、千代田線　新御茶ノ水も可）<br><br>[募集人員]<br>1名<br><br>[着任時期]<br>2015年4月1日（ご希望により早期開始も可能）<br></p></div>","研究分野":"医歯薬学:医歯薬学:生物学","            小分類":"生物科学","職種":"\r\n            \r\n            研究員・ポスドク相当\r\n            \r\n            ","":"研究員・ポスドク相当","勤務形態":"常勤（任期あり）,1年毎の更新（年度末）","勤務地":"関東 -,東京都","応募資格":"１．博士の学位を有する方２．英文誌の筆頭論文を持つ方３．協調性がありコミュニケーション能力に優れた方","待遇":"月26万円　（私学共済加入可）","募集期間":"2014年12月26日 ～,2015年01月25日 必着,決定次第終了致します","応募・選考・結果通知・連絡先":"[応募方法(書類送付先も含む)]E-mail添付にて①、②を下ご送信下さい。E-mailの件名に「研究員応募申込」と記載し、応募書類はMicrosoft WordまたはPDF形式にて送信してください。①履歴書（写真貼付）　　②業績リスト（本公募の審査のみに使用します。書類の返却は致しません）[選考内容(選考方法、採否の決定)、結果通知方法]締切日から2週間以内に結果を通知致します。[連絡先(担当者所属、役職、氏名、e-mail、電話番号)] ※重要順天堂大学医学部耳鼻咽喉科学講座担当者連絡先：jibikakoubo@juntendo.ac.jpお問い合わせはE-mailにてお願いいたします。","Web応募":"不可"}}