{"time":"2014-06-16 00:00:00 -0700","subject":"山梨大学大学院医学工学総合研究部・工学学域・機電情報システム工学系教員（助教）の公募","period":"NA:2014-10-31:NA","place":["山梨県"],"place_en":["Yamanashi"],"genre":"工学:工学","institution":"山梨大学","title":"助教相当","id":"D114060692","data":{"データ番号":"D114060692","公開開始日":"2014年06月16日","更新日":"2014年06月16日","求人件名":"山梨大学大学院医学工学総合研究部・工学学域・機電情報システム工学系教員（助教）の公募","機関名":"山梨大学","機関または部署":"http://www.eng.yamanashi.ac.jp/","部署名":"大学院医学工学総合研究部","機関種別":"国立大学","求人内容":"<div class=\"margin-01\">[機関の説明(募集の背景、機関の詳細、プロジェクトの説明等)]<br>大学院医学工学総合研究部（工学学域・機電情報システム工学系）の常勤助教の公募<br><br>専門分野：制御工学，ロボット工学，組込ソフトウェア工学<br><br><br>[仕事内容(業務内容、担当科目等)]<br>１．工学部（情報メカトロニクス工学科）及び修士課程コンピュータ・メディア工学専攻において実験・実習・演習等を担当するとともに，学生の教育研究指導を行う．<br><br>２．特に情報メカトロニクス工学科の理念に基づき，ロボットなどの対象機械の動作を理解した上でアナログ回路を作成する教育を行う．<br><br>授業担当科目：アナログ回路，デジタル回路，組み込みアーキテクチャなど<br><br>[勤務地住所等]<br>〒400-8511　甲府市武田4-3-11<br><br>[募集人員]<br>1名<br>助教<br><br>[着任時期]<br>2015年04月01日<br><br>,</div>","研究分野":"工学:工学","            小分類":"機械工学","職種":"\r\n            \r\n            助教相当\r\n            \r\n            ","":"助教相当","勤務形態":"常勤（任期なし）","勤務地":"北陸・甲信越 -,山梨県","応募資格":"(1) 博士の学位を有する方もしくは着任時までに取得見込みの方(2) 上記専門分野における研究と教育に意欲があり，学生の指導に熱意のある方","待遇":"国立大学法人山梨大学の規定による","募集期間":"2014年10月31日 必着","応募・選考・結果通知・連絡先":"[応募方法(書類送付先も含む)](1) 履歴書（学歴、職歴、研究歴、教育歴、賞罰等を記載のこと．また写真貼付，連絡先とe-mailアドレスを明記すること）(2) 研究業績リスト（学術論文，国際会議論文，解説・総説，著書，特許，口頭発表など）(3) 主要論文（10編以内）の別刷り（コピーでも可）(4) 外部研究資金の獲得状況（科学研究費，共同研究，受託研究など）(5) 現在までの研究概要（1,000字程度）(6) 今後の研究計画（1,000字程度）(7) 推薦書１通（自薦の場合は意見を求めることができる方２名の氏名及び連絡先）〒400-8511  山梨県甲府市武田4-3-11山梨大学工学部情報メカトロニクス工学科事務室　宛※ 封筒表に「教員公募書類在中」と朱書し，簡易書留で郵送願います．※ 原則として提出書類は返却いたしません．[選考内容(選考方法、採否の決定)、結果通知方法]提出書類による一次選考の後，一次合格者に対して面接による二次選考を行います．[連絡先(担当者所属、役職、氏名、e-mail、電話番号)] ※重要山梨大学大学院医学工学総合研究部　教授　寺田　英嗣TEL: 055-220-8452 FAX: 055-220-8452  E-mail: terada@yamanashi.ac.jp","備考":"山梨大学では「女性研究者研究活動支援事業」を推進しています．学内には，女性研究者支援室を設置し，女性研究者に対する全学的なサポート体制を整備しています．http://www.conohana.yamanashi.ac.jp/","Web応募":"不可"}}