{"time":"2014-12-19 00:00:00 -0800","subject":"【客員研究員】基板上質量選別クラスタの作製と解析","period":"NA:2015-03-31:採用が決まり次第終了","place":["愛知県"],"place_en":["Aichi"],"genre":"総合理工:総合理工:化学","institution":"株式会社豊田中央研究所","title":"研究員・ポスドク相当","id":"D114121117","data":{"データ番号":"D114121117","公開開始日":"2014年12月19日","更新日":"2014年12月19日","求人件名":"【客員研究員】基板上質量選別クラスタの作製と解析","機関名":"株式会社豊田中央研究所","機関または部署":"http://www.tytlabs.co.jp","機関種別":"民間企業","公募の":"http://www.tytlabs.co.jp/recr/kyakuin.html","求人内容":"<div class=\"margin-01\">[仕事内容]<br>基板上質量選別クラスタの作製と解析<br>専門領域、専門分野：触媒表面化学、化学<br><br>[勤務地]<br>480-1192　愛知県長久手市横道41-1<br><br>[募集人員]<br>1名<br><br>[着任時期]<br>2015/04/01～<br>※応相談<br>,</div>","研究分野":"総合理工:総合理工:化学","            小分類":"基礎化学","職種":"\r\n            \r\n            研究員・ポスドク相当\r\n            \r\n            ","":"研究員・ポスドク相当","勤務形態":"常勤（任期あり）,1年毎の契約更新、最長3年","勤務地":"東海 -,愛知県","応募資格":"表面化学またはクラスタ科学に関する研究経験があり、博士の学位を有する方。特にSTMに関連した論文執筆経験のある方を歓迎","待遇":"【給与】年俸制　※経験・能力を考慮し、当社規定により決定します。【勤務時間】裁量労働制　※標準勤務時間　8:30～17:30　（12：00～13：00休憩） 【休日・休暇】年間121日（土日、GW、夏季休暇、年末・年始休暇）、年次有給休暇 【制度】住宅費補助、通勤費補助、財形貯蓄 【保険】各種社会保険加入、各種団体保険加入","募集期間":"2015年03月31日 必着,採用が決まり次第終了","応募・選考・結果通知・連絡先":"応募職種・職務内容を明記の上、下記書類をお送りください。　■履歴書（写真添付）　■職務歴（研究実績）　■論文リスト　■主要論文別刷（コピー可）等※応募書類は返却いたしません。応募の秘密は厳守いたします。選考内容：書類審査、面接、適性検査書類送付先およびお問合せ先：　〒480-1192　愛知県長久手市横道41-1　株式会社豊田中央研究所　人材開発G　採用担当","Web応募":"不可","機関紹介サイト":"当該機関の外部サイト情報を新規ウィンドウで表示します。"}}