{"time":"2015-01-20 00:00:00 -0800","subject":"京都大学大学院教育学研究科教員（准教授）の公募","period":"NA:2015-02-23:NA","place":["京都府"],"place_en":["Kyoto"],"genre":"社会科学","institution":"京都大学","title":"准教授・常勤専任講師相当","id":"D115010806","data":{"データ番号":"D115010806","公開開始日":"2015年01月20日","更新日":"2015年01月20日","求人件名":"京都大学大学院教育学研究科教員（准教授）の公募","機関名":"京都大学","機関または部署":"http://www.educ.kyoto-u.ac.jp/","部署名":"大学院教育学研究科","機関種別":"国立大学","求人内容":"<div class=\"margin-01\"><p style=\"word-wrap: break-word;\">[機関の説明(募集の背景、機関の詳細、プロジェクトの説明等)]<br>京都大学大学院教育学研究科は下記要領により、教育学講座准教授１名を募集いたします。<br><br>[仕事内容(業務内容、担当科目等)]<br>専攻分野：教育史分野 <br>担当科目：教育史関連科目（学部「教育史概論」「教育史専門ゼミナール」、大学院「教育史特論」「教育史演習」「教育学研究」等）<br><br>[勤務地住所等]<br>京都大学吉田キャンパス（京都市左京区吉田本町）<br><br>[募集人員]<br>１名<br><br>[着任時期]<br>平成２８年４月１日（金）<br></p></div>","研究分野":"社会科学","            小分類":"教育学","職種":"\r\n            \r\n            准教授・常勤専任講師相当\r\n            \r\n            ","":"准教授・常勤専任講師相当","勤務形態":"常勤（任期なし）","勤務地":"近畿 -,京都府","応募資格":"（１）博士の学位を取得している者、またはこれと同等の業績を有する者（２）単著を有することが望ましい（３）大学院の教育研究を担当できる者","待遇":"専門業務型裁量労働制（週３８時間４５分相当、１日７時間４５分相当）休日：土・日曜日、祝日、年末年始、創立記念日および夏季一斉休業日給与・手当：本学支給基準に基づき支給社会保険：文部科学省共済組合、雇用保険および労災保険に加入","募集期間":"2015年02月23日 必着,午後５時　書留郵便必着","応募・選考・結果通知・連絡先":"[応募方法(書類送付先も含む)](1)履歴書（写真貼付、メール・アドレスを記入）(2)学術研究業績目録（以下の項目ごとに分けて記載すること）　1) 著書　2) 学術論文（査読の有無を記すこと）　3) 翻訳書　4) 研究報告書・論評等　5) その他の刊行物　6) 学会発表歴(3)主要な業績3編（著書の場合は原本、論文等の場合は抜き刷りまたはコピー）。必要に応じて他の業績の提出を求めることがあります。(4)本学での教育・研究への抱負（2000字程度・書式自由）（宛先）〒606-8501　京都市左京区吉田本町　京都大学大学院教育学研究科総務掛※封筒の表に「教育学講座准教授応募書類在中」と朱書きし、書留郵便で送付のこと〇提出書類は、厳重に保管・管理し、審査終了後は責任をもって破棄します。また、提出書類に含まれる個人情報は個人情報保護法に基づき、教員選考以外の目的には使用いたしません。〇応募書類等は、選考終了後も返却しませんので、あらかじめご了承願います。[選考内容(選考方法、採否の決定)、結果通知方法]書類選考によるが、必要に応じて、面接を行うことがあります。（面接実施の際の旅費は応募者の負担とします。）[連絡先(担当者所属、役職、氏名、e-mail、電話番号)] ※重要〒606-8501　京都市左京区吉田本町京都大学大学院教育学研究科　教育学講座　駒込　武FAX : 075-753-3034E-mail：komagome.takeshi.5m*kyoto-u.ac.jp（*を@に変えて下さい） 注：電話による問い合わせは、受け付けできません。","備考":"京都大学は男女共同参画を推進しております。女性研究者の積極的な応募を期待します。","Web応募":"不可"}}