{"time":"2014-10-03 00:00:00 -0700","subject":"医学部　第１解剖学講座担当　教授候補者の公募","period":"2014年11月30日 消印有効","place":["福岡県"],"place_en":["Fukuoka"],"genre":"医歯薬学","institution":"産業医科大学","title":"教授相当","id":"D114100197","data":{"データ番号":"D114100197","公開開始日":"2014年10月03日","更新日":"2014年10月03日","求人件名":"医学部　第１解剖学講座担当　教授候補者の公募","機関名":"産業医科大学","機関または部署":"http://www.uoeh-u.ac.jp/","部署名":"医学部","機関種別":"私立大学","求人内容":"<div class=\"margin-01\">　このたび、第1解剖学講座担当教授　菊田　彰夫が、平成27年3月31日付けで退職いたしますので、その後任教授候補者を別紙のとおり公募することになりました。<br>　つきましては、解剖学教育、特に人体系統（肉眼）解剖学および人体系統解剖学実習に十分な経験を有し、且つ、研究はもとより学生の教育に熱意のある方が貴機関または関係機関におられましたらご推薦いただきますようお願い申し上げます。<br>　なお、人体系統解剖学実習をご担当いただくにあたり、篤志献体に関する業務の担当もお願いすることになります。<br>　現在、本学医学部の解剖学教育においては、第1解剖学講座は、骨学、筋学、神経解剖学および人体系統解剖学実習を、第2解剖学（森本景之 教授）は内臓学、脈管学、人体発生学および組織学並びに組織学実習を分担しております。<br>　本学は平成18年4月から任期制を導入しており、教授については任期5年、再任は4回限り（定年65歳）となっていることを申し添えます。ただし、契約期間を通算した期間が10年を超えるときは、申込みにより期間の定めのない労働契約（無期労働契約）へ転換することが可能です。<br><br><br>所属・職名等：医学部　第１解剖学講座　教授　1名<br><br><br>[仕事内容(業務内容、担当科目等)]<br>解剖学（授業内容「解剖学」）<br><br>[勤務地住所等]<br><br><br>[募集人員]<br>1名<br><br>[着任時期]<br><br>,</div>","研究分野":"医歯薬学","            小分類":"基礎医学","職種":"\r\n            \r\n            教授相当\r\n            \r\n            ","":"教授相当","勤務形態":"常勤（任期あり）","勤務地":"九州・沖縄 -,福岡県","応募資格":"(1) 大学設置基準に規定する教授の資格をもつ者(2) 専門分野における教育・研究に豊富な経験と熱意をもつ者(3) 本学の使命である産業医学の振興・発展と優れた産業医の養成に寄与できる者","待遇":"任期：教授の任期は5年、再任は4回限り（定年65歳）。ただし、契約期間を通算した期間が10年を超えるときは、申込みにより期間の定めのない労働契約（無期労働契約）へ転換することができる。","募集期間":"2014年11月30日 消印有効","応募・選考・結果通知・連絡先":"[応募方法(書類送付先も含む)](1) 推薦書（所定様式） 1部（複数可）(2) 教員個人調書（履歴書、教育研究実績書）（所定様式） 1部(3) インパクトファクター（IF）集計表（所定様式） 1部(4) 論文の別刷（主要論文10編） 各1部（プリント）(5) 現在までの研究活動および将来の研究に対する抱負（1200字程度） 1部（A4版１枚）(6) 医学教育および産業医養成についての抱負（1200字程度） 1部（A4版１枚）(7) 人体系統解剖学に関する実習および教育セミナー等の実績（所定様式） 1部(8) 学位記（写）(2)、(3)、(4)、(7)については、印刷したものを各1部以外に下記ファイル形式で保存したCD（同じものを2枚）を添付のこと。   ・(2) ワードファイル（MSワード2003以上）およびPDFファイル   ・(3)エクセルファイル（MSエクセル2003以上）およびPDFファイル   ・(4)PDFファイル   ・(7)エクセルファイル（MSエクセル2003以上）およびPDFファイル※ 所定様式については、下記照会先にご請求いただくか、本学ホームページ（http://www.uoeh-u.ac.jp/）「採用希望の方」から、「教職員採用情報」の当募集情報をクリック、「詳細（提出書類）」からダウンロードして下さい。※　下記添付書類からもダウンロードできます。提出先および照会先：　学校法人 産業医科大学　総務部人事課 医学部 第1解剖学講座担当教授候補者選考委員会　　〒807-8555　北九州市八幡西区医生ヶ丘1番1号　　Tel: 093(691)7112（直通）Fax: 093(691)7490※　郵送（書留）に限り受け付けます。　　　封筒の表に「医学部 第1解剖学講座担当教授候補者応募書類 在中」と朱書きして下さい。[選考内容(選考方法、採否の決定)、結果通知方法]面接および講演等をお願いすることがあります。[連絡先(担当者所属、役職、氏名、e-mail、電話番号)] ※重要　学校法人 産業医科大学　総務部人事課 医学部 第１解剖学講座担当教授候補者選考委員会　　〒807-8555　北九州市八幡西区医生ケ丘1番1号　　Tel: 093(691)7112（直通）Fax: 093(691)7490","添付書類":"1.第１解剖学教授 公募要項.pdf,2.第１解剖学教授 推薦書・個人調書.doc,3.第１解剖学教授 ｲﾝﾊﾟｸﾄﾌｧｸﾀｰ集計表.xls,4.第１解剖学教授 人体系統解剖学に関する実績.xls","備考":"お送りいただきました選考関係書類は、選考後お返しいたしません。","Web応募":"不可"}}