{"time":"2014-09-18 00:00:00 -0700","subject":"薬学部 助教の募集（「分子神経生物学、ゲノム編集」および関連分野）","period":"NA:2014-11-28:NA","place":["滋賀県"],"place_en":["Shiga"],"genre":"医歯薬学:医歯薬学","institution":"立命館大学","title":"助教相当","id":"D114090807","data":{"データ番号":"D114090807","公開開始日":"2014年09月18日","更新日":"2014年09月18日","求人件名":"薬学部 助教の募集（「分子神経生物学、ゲノム編集」および関連分野）","機関名":"立命館大学","機関または部署":"http://www.ritsumei.ac.jp/ph/","部署名":"薬学部","機関種別":"私立大学","求人内容":"<div class=\"margin-01\">[機関の説明(募集の背景、機関の詳細、プロジェクトの説明等)]<br>【任用職名】 薬学部 薬学科 助教<br>【募集人数】 1名 <br>【専門分野】 「分子神経生物学、ゲノム編集」および関連分野<br><br>[仕事内容(業務内容、担当科目等)]<br>上記の分野に関連する専門科目、実習科目と生物系教養科目等<br>＊ゲノム機能学研究室に所属し、稲津哲也教授とともに教育・研究に携わっていただきます。<br><br><br>[勤務地住所等]<br>〒525-8577 滋賀県草津市野路東1-1-1<br><br>[募集人員]<br>1名<br><br>[着任時期]<br>2015年04月01日<br><br>,</div>","研究分野":"医歯薬学:医歯薬学","            小分類":"基礎医学","職種":"\r\n            \r\n            助教相当\r\n            \r\n            ","":"助教相当","勤務形態":"常勤（任期あり）,任期: 2015年4月1日～2020年3月31日（5年間、再任不可）","勤務地":"近畿 -,滋賀県","応募資格":"① 本学での教育・研究に熱意を持っている方。② 任用時に博士の学位を有し、上記の専門分野の研究業績がある方。③ 薬剤師（もしくは医師、歯科医師）免許を取得していることが望ましい。","待遇":"本学給与規程等にもとづき支給します。","募集期間":"2014年11月28日 必着,必着","応募・選考・結果通知・連絡先":"[応募方法(書類送付先も含む)]① 履歴書（様式1、様式2 によること）② 教育研究業績書（様式3、様式4-1, 4-2 によること）＊①、②の書式は本学ホームページよりダウンロードできます。　　http://www.ritsumei.jp/job/index_j.html③ 最終学歴の学位証明書④ 主要研究業績（著書または論文）5編以内（コピー、抜刷可）⑤ 現在までの研究内容の説明と今後の研究計画の概要（1,500字程度、書式自由）、および本学部において教育・研究を希望する理由を記載した書類（1,000字程度、書式自由）⑥ 科研費等の研究補助金の取得状況を記載した書類（書式自由）⑦ 応募者についての参考意見を伺える方2名の氏名・所属・連絡先ならびに応募者との関係を記載した書類（書式自由）※提出書類は返却いたしませんで、あらかじめご了承ください。なお、応募に際しご提出いただいた個人情報は、本学の規程に従って適切に管理し、採用選考の目的以外には使用いたしません。[選考内容(選考方法、採否の決定)、結果通知方法](1) 第1次選考　書類審査 (2) 第2次選考　面接[連絡先(担当者所属、役職、氏名、e-mail、電話番号)] ※重要【書類の提出先および問合せ先】〒525-8577　滋賀県草津市野路東1-1-1　立命館大学　薬学部 薬学科　ゲノム機能学研究室　稲津　哲也　宛E-mail：tinazu@fc.ritsumei.ac.jp　Tel.: 077-561-2561※応募封筒には『薬学部薬学科 教員応募（分子神経生物学等）書類在中』と朱書きして、必ず書留にて郵送してください。※お問い合わせは、Ｅメールでお願いします。","Web応募":"不可"}}