{"time":"2014-10-08 00:00:00 -0700","subject":"東京大学宇宙線研究所助教（観測的宇宙論）の公募について","period":"2014-10-03:2014-12-01:NA","place":["千葉県"],"place_en":["Chiba"],"genre":"数物系科学:数物系科学","institution":"東京大学","title":"助教相当","id":"D114100625","data":{"データ番号":"D114100625","公開開始日":"2014年10月08日","更新日":"2014年10月08日","求人件名":"東京大学宇宙線研究所助教（観測的宇宙論）の公募について","機関名":"東京大学","機関または部署":"http://www.icrr.u-tokyo.ac.jp/index.html","部署名":"東京大学宇宙線研究所","機関種別":"国立大学","公募の":"http://www.icrr.u-tokyo.ac.jp/2014/10/02171528.html","求人内容":"<div class=\"margin-01\">[機関の説明(募集の背景、機関の詳細、プロジェクトの説明等)]<br><br><br>[仕事内容(業務内容、担当科目等)]<br>宇宙論および銀河形成に関する光赤外線観測を通して広義の宇宙線研究に従事する。<br>特に、本研究所の観測的宇宙論グループの教員と協力して、広領域深宇宙探査を推進する。また、観測的宇宙論研究に関する将来計画にも関わっていただきます。<br><br>[勤務地住所等]<br>宇宙線研究所（千葉県柏市）<br><br>[募集人員]<br>助教1名<br><br><br>[着任時期]<br>平成２７年４月１日以降なるべく早い時期<br>,</div>","研究分野":"数物系科学:数物系科学","            小分類":"天文学","職種":"\r\n            \r\n            助教相当\r\n            \r\n            ","":"助教相当","勤務形態":"常勤（任期なし）","勤務地":"関東 -,千葉県","応募資格":"博士号を取得している者。","待遇":"職名：東京大学宇宙線研究所助教として雇用。給与：東京大学教職員給与規則に基づき、経歴により決定。勤務時間休日：裁量労働制保険：文部科学省共済組合加入","募集期間":"2014年10月03日 ～,2014年12月01日 必着,12月1日17時書類必着","応募・選考・結果通知・連絡先":"[応募方法(書類送付先も含む)]○応募締切　平成26年12月1日（月）17時必着○提出書類等応募者は以下の（１）から（５）までの書類を、Eメイルに添付（電子ファイル）で提出してください。（６）の意見書は、作成者から直接Ｅメイルに添付で応募締切日までに提出してください。応募書類・意見書のファイル形式はpdfとします。Eメイルによる提出に対しては、受信した旨の返信をしますので、必ず当方からの返信の有無を確認してください。やむを得ない場合は書留での郵送でも結構です。郵送の場合は封書に「教員応募書類（観測的宇宙論）」と朱書きしてください。(1)履歴書（市販の様式相当、博士号取得年月およびＥメイルアドレスを必ず記入してください。）(2)研究歴（A４版３頁以内）(3)業績リスト(論文リスト、口頭での発表を含めた研究発表リスト等)、及び主要論文（３編以内）。提出する論文については論文リストに印を付け、一目でわかるようにすること。(4)着任可能時期(5)着任後の研究計画（A４版３頁以内）(6)意見書または推薦書２通○送付先E メイル application_at_icrr.u-tokyo.ac.jp（メイルを送信する際は_at_を@に直してください）郵送 〒277-8582千葉県柏市柏の葉５－１－５東京大学宇宙線研究所 総務係[選考内容(選考方法、採否の決定)、結果通知方法]選考委員会による書類選考（第一次審査）を行い、最終選考は面接によります。（面接を受けていただく方には詳細を連絡します。）[連絡先(担当者所属、役職、氏名、e-mail、電話番号)] ※重要問い合わせ先同研究所長 梶田隆章E メイル：kajita_at_icrr.u-tokyo.ac.jp（メイルを送信する際は_at_を@に直してください）電話（０４）－７１３６－３１００職務内容に関しては、以下へ観測的宇宙論グループ准教授 大内正己電話（０４）－７１３６－３１５７Ｅメイル ouchims_at_icrr.u-tokyo.ac.jp（メイルを送信する際は_at_を@に直してください）","備考":"「東京大学男女共同参画加速のための宣言」に基づき女性の応募を歓迎します。","Web応募":"可"}}