{"time":"2014-11-01 00:00:00 -0700","subject":"留学生別科　常勤講師（日本語講師）","period":"2014-11-01:2014-12-15:書類選考の上、随時面接を行います。","place":["愛媛県"],"place_en":["Ehime"],"genre":"人文学:人文学:人文学","institution":"環太平洋大学短期大学部","title":"准教授・常勤専任講師相当","id":"D114102314","data":{"データ番号":"D114102314","公開開始日":"2014年11月01日","更新日":"2014年11月01日","求人件名":"留学生別科　常勤講師（日本語講師）","機関名":"環太平洋大学短期大学部","機関または部署":"http://www.aitan.ac.jp/","部署名":"留学生別科（グローバルスタディーセンター）","機関種別":"短期大学","求人内容":"<div class=\"margin-01\">[機関の説明(募集の背景、機関の詳細、プロジェクトの説明等)]<br>日本語講師（専任）の募集<br><br>環太平洋大学短期大学部が開設する留学生別科（グローバルスタディーセンター）の日本語専任講師を募集します。日本語学習歴の浅い留学生に対して、日本語指導と大学進学支援を行います。<br>本科の国際商務課程と連携して、授業運営や学生指導、日本語の講義を担当していただきます。<br><br>職名：常勤講師（任期制）<br><br>専門分野：国際・日本語教育<br><br>担当科目：日本語・検定対策など<br><br><br>[仕事内容(業務内容、担当科目等)]<br>①グローバルスタディーセンターの授業運営<br>②学校行事・学科業務及び学生指導<br>③当該分野に関する領域の研究<br>④本科の授業も状況により担当していただきます。<br><br>[勤務地住所等]<br>愛媛県宇和島市伊吹町馬場４２１<br>ＩＰＵ環太平洋大学 短期大学部<br><br>[募集人員]<br>若干名<br><br>[着任時期]<br>２０１５年３月<br>着任日は応相談<br>,</div>","研究分野":"人文学:人文学:人文学","            小分類":"日本語教育","職種":"\r\n            \r\n            准教授・常勤専任講師相当\r\n            \r\n            ","":"准教授・常勤専任講師相当","勤務形態":"常勤（任期あり）","勤務地":"四国 -,愛媛県","応募資格":"①日本語教育の教歴がある方（プライベートレッスンは除く）②４年制大学卒業以上の方、　またはこれと同等以上の学歴を有する方","待遇":"①雇用形態：常勤契約（契約職員）※正職員登用あり②給与：月額22万円～30万円程度　　　　（経験、能力により本学給与規定を基に相談）　　　　賞与（年2回各1ヶ月分）③社会保険：私学共済加入④その他手当：通勤手当（マイカー通勤相談可）","募集期間":"2014年11月01日 ～,2014年12月15日 必着,書類選考の上、随時面接を行います。","応募・選考・結果通知・連絡先":"[応募方法(書類送付先も含む)]写真付き履歴書、研究業績書、資格または免許などの写し（コピー）を下記住所へご郵送ください。〒651-0084　兵庫県神戸市中央区磯辺通4-1-5　アンビシャスビル3Ｆ　学校法人創志学園　人事課　ＩＰＵ短大日本語講師募集係※到着より2週間程度で書類選考合否をお知らせします。※ご応募書類は原則当方責任において募集活動終了時に破棄します。[選考内容(選考方法、採否の決定)、結果通知方法]書類選考→一次・二次選考（個別面接、模擬授業、筆記）→最終選考（個別面接）[連絡先(担当者所属、役職、氏名、e-mail、電話番号)] 法人本部人事課　078-262-0830（平日10-17時）recruit@efg.co.jp","備考":"大学行事により土日祝日に出勤あり（振替制）日本語学習意欲の高い留学生への講義ならびに進学指導・生活指導など積極的に業務に取り組める方を募集しています。","Web応募":"不可"}}