{"time":"2014-09-06 00:00:00 -0700","subject":"教員の公募（看護学科：成人看護学の教授）","period":"NA:2014-10-14:NA","place":["香川県"],"place_en":["Kagawa"],"genre":"医歯薬学","institution":"香川県立保健医療大学","title":"教授相当","id":"D114090234","data":{"データ番号":"D114090234","公開開始日":"2014年09月06日","更新日":"2014年09月06日","求人件名":"教員の公募（看護学科：成人看護学の教授）","機関名":"香川県立保健医療大学","機関種別":"公立大学","求人内容":"<div class=\"margin-01\">[機関の説明(募集の背景、機関の詳細、プロジェクトの説明等)]<br><br><br>[仕事内容(業務内容、担当科目等)]<br>担当分野<br>　成人看護学　<br>担当科目<br>　（学部）成人看護学Ⅰ・Ⅱ・Ⅲ（このうち主として慢性期を担当）、成人看護学実習、専門ゼミナール、看護トピックス（等）<br>　（大学院）成人老年看護学特論、成人老年看護学演習、特別研究<br><br><br>[勤務地住所等]<br>香川県高松市牟礼町原２８１－１<br><br>[募集人員]<br>1名<br><br>[着任時期]<br>2015年04月01日<br><br>,</div>","研究分野":"医歯薬学","            小分類":"看護学","職種":"\r\n            \r\n            教授相当\r\n            \r\n            ","":"教授相当","勤務形態":"常勤（任期なし）","勤務地":"四国 -,香川県","応募資格":"次のいずれにも該当する方（1）博士の学位を有する者（2）大学等において１０年以上の教育歴又は研究歴を有すること（助手あるいは大学院在籍期間を含む）（3）看護師の資格を有すること（4）３年以上の臨床経験を有すること（5）地方公務員法第１６条に規定する欠格条項に該当しないこと","募集期間":"2014年10月14日 必着","応募・選考・結果通知・連絡先":"[応募方法(書類送付先も含む)]提出書類 （１）履歴書（別添様式） （２）教育研究業績書（別添様式　著書、学術論文の他学位論文についても記載すること） （３）主要論文　１０編以上の別刷又はコピー　各６部 （４）教育、研究、地域貢献等に対する抱負（様式は任意、２０００字程度） （５）看護師免許証の写提出期限　２０１４年１０月１４日（火）　午後５時（必着）提出先　〒７６１－０１２３　香川県高松市牟礼町原２８１－１　香川県立保健医療大学　事務局　　※郵送の場合は必ず書留にて送付してください[選考内容(選考方法、採否の決定)、結果通知方法]書類選考を行い、必要に応じて面接を本学にて行います。[連絡先(担当者所属、役職、氏名、e-mail、電話番号)] ※重要香川県立保健医療大学事務局　　担当　佐藤sato-t@chs.pref.kagawa.jpTEL:087-870-1212FAX:087-870-1202","添付書類":"1.履歴書.doc,2.教育研究業績書.doc,3.研究業績等に関する事項の記載例.pdf","Web応募":"不可"}}