{"time":"2014-08-23 00:00:00 -0700","subject":"ポスドク募集（谷口研究室）","period":"NA:2014-12-31:ただし採用者決定次第募集を打ち切ります。","place":"その他 -,その他","place_en":null,"genre":"生物学:医歯薬学:総合生物","institution":"マックスプランクフロリダ研究所","title":"研究員・ポスドク相当","id":"D114080997","data":{"データ番号":"D114080997","公開開始日":"2014年08月23日","更新日":"2014年08月25日","求人件名":"ポスドク募集（谷口研究室）","機関名":"マックスプランクフロリダ研究所","機関または部署":"http://www.maxplanckflorida.org/hiroki-taniguchi.html","部署名":"development and function of inhibirtory neural circuits","機関種別":"海外研究機関","求人内容":"<div class=\"margin-01\">[機関の説明(募集の背景、機関の詳細、プロジェクトの説明等)]<br>Max Planck Florida Institute(MPFI)、谷口研究室では、現在新たにポスドク１名を募集しております。恵まれた研究環境を生かし、オリジナリティの高い研究を追求し、その過程を“いっしょに楽しめる方”を歓迎します。将来、研究室主宰者となり、神経回路研究の潮流を自分で作りたいと考えている方、この機会を利用してみませんか？ <br><br>MPFIは、２年前、米国フロリダに設立された神経回路研究に特化した新しい研究所です。所内では米国内外の著名研究者によるセミナーが頻繁に行われ、キャンパス内のScripps Florida Institute, Florida Atlantic Universityとも活発な研究交流が行われています。また、ドイツMax Planck Societyの一部であることから、米国にいながら“Max Planck流”を体感できるというのも当研究所の大きな魅力の１つとなっています。<br><br><br>[仕事内容(業務内容、担当科目等)]<br>大脳抑制性神経細胞には多くのサブタイプが存在します。それぞれのサブタイプは、多様な神経回路機能において、特有の働きをしていることが示唆されています。したがって、大脳抑制性神経細胞サブタイプ多様性の生成メカニズム、機能的意義を明らかにすることは、脳科学における最重要課題の１つとなっています。われわれは、マウス遺伝学、分子生物学、ウイルス学、イメージング技術を活用し、大脳抑制性神経細胞サブタイプの運命決定メカニズム、神経回路発達、高次機能における役割を理解しようとしています。今回の募集では、特に、大脳抑制性神経細胞サブタイプの学習、機能的回路発達における神経活動、構造的可塑性に興味を持たれている方を募集します。<br><br>(参考文献)<br>Taniguchi et al.,Neuron, 2011<br>Taniguchi et al.,Science, 2013<br>Taniguchi et al.,Front. Cell. Neurosci, 2014<br><br>[勤務地住所等]<br>One Max Planck Way<br>Jupiter, FL, USA 33458<br><br>米国フロリダ州ジュピター。海と自然に囲まれた年中暖かな場所にあります。トップクラスの公立学校の学区内にあり、治安もよく、ご家族のおられる方も安心かと思います。<br><br>[募集人員]<br>1名<br><br>[着任時期]<br>2015年04月01日<br>相談に応じます<br>,</div>","研究分野":"生物学:医歯薬学:総合生物","            小分類":"神経科学","職種":"\r\n            \r\n            研究員・ポスドク相当\r\n            \r\n            ","":"研究員・ポスドク相当","勤務形態":"非常勤（任期あり）,２年後更新あり","勤務地":"その他 -,その他","応募資格":"博士課程修了、もしくは修了見込み者。必須ではありませんが、生体内での脳機能研究、二光子顕微鏡イメージング経験者を歓迎します。","待遇":"MPFIの規定に準ずる。","募集期間":"2014年12月31日 必着,ただし採用者決定次第募集を打ち切ります。","応募・選考・結果通知・連絡先":"[応募方法(書類送付先も含む)]1.CV（業績リスト、実験手技、推薦者３名の連絡先を含む）2.これまでの研究内容（1-2ページ）3.志望動機（1-2ページ）以上を英文でまとめ、PDFをe-mailで送付してください。質問等がありましたら、応募前のコンタクトも大歓迎です（日本語可）。[選考内容(選考方法、採否の決定)、結果通知方法]書類選考後、通過者にはSkype面接、当地でのセミナーをお願いします。[連絡先(担当者所属、役職、氏名、e-mail、電話番号)] ※重要taniguchimpfi@gmail.comtel:1-561-972-9260","Web応募":"不可"}}