{"time":"2014-10-03 00:00:00 -0700","subject":"助教（専任または特任）公募「成人看護学」","period":"2014-10-01:2014-10-27:NA","place":"関東 -,神奈川県","place_en":"Kanagawa","genre":"医歯薬学","institution":"東海大学","title":"助教相当","id":"D114100108","data":{"データ番号":"D114100108","公開開始日":"2014年10月03日","更新日":"2014年10月03日","求人件名":"助教（専任または特任）公募「成人看護学」","機関名":"東海大学","部署名":"健康科学部看護学科","機関種別":"私立大学","求人内容":"<div class=\"margin-01\">[機関の説明(募集の背景、機関の詳細、プロジェクトの説明等)]<br>職位・人数：助教（専任または特任）　１名<br>専門分野　：成人看護学<br>担当科目　：成人看護学の講義・実習指導並びに関連科目<br>　　　　　　<br><br>[仕事内容(業務内容、担当科目等)]<br><br><br>[勤務地住所等]<br>〒２５９－１１９３　神奈川県伊勢原市下糟屋１４３<br><br>[募集人員]<br>1名<br>助教（専任または特任）<br><br>[着任時期]<br>2015年04月01日<br><br>,</div>","研究分野":"医歯薬学","            小分類":"看護学","職種":"\r\n            \r\n            助教相当\r\n            \r\n            ","":"助教相当","勤務形態":"常勤（任期なし）,特任の場合は任期あり","勤務地":"関東 -,神奈川県","応募資格":"次の①～⑤の条件を全て満たす方①修士が望ましい。②臨地実践歴3年以上。③領域外科目も担当できることが望ましい。④看護師免許を有すること。⑤保健師免許を有することが望ましい。","待遇":"（１）給与：本学給与規程による。（２）社会保険：日本私立学校振興・共済事業団（医療保険・年金）、雇用保険、労災保険","募集期間":"2014年10月01日 ～,2014年10月27日 必着","応募・選考・結果通知・連絡先":"[応募方法(書類送付先も含む)]①履歴書（本学所定用紙、写真添付）１部②教育研究業績（本学所定用紙）１部③主要論文の別刷（コピー可）５編以内　各１部④自己の研究の学問的位置づけ及びそれと看護教育との関わりについて（Ａ４横書き、２０００字程度）＊提出書類に含まれる個人情報は、選考及び採用以外の目的には使用致しません。なお、応募書類は返却いたしません。提出期限：２０１４年１０月２７日（月）必着提出先：〒２５９－１１９３　神奈川県伊勢原市下糟屋１４３　　　　東海大学伊勢原校舎　伊勢原教育計画部事務室　　　　看護学科公募担当＊郵送に際しては、「成人看護学領域教員公募書類在中」と　表記し、簡易書留にてご送付下さい。問い合わせ先：東海大学健康科学部看護学科教授　城生　弘美ＴＥＬ＆ＦＡＸ：０４６３－９０－２０５９Ｅ－ＭＡＩＬ：kangojimu@mars.ihs.u-tokai.ac.jp[選考内容(選考方法、採否の決定)、結果通知方法]①第１次選考：当該学科による書類審査②第２次選考：学科面接＊その後、学長面接・総長面接があります。[連絡先(担当者所属、役職、氏名、e-mail、電話番号)] ※重要〒２５９－１１９３神奈川県伊勢原市下糟屋１４３東海大学健康科学部看護学科　教授　城生　弘美ＴＥＬ＆ＦＡＸ：０４６３－９０－２０５９Ｅ－ＭＡＩＬ：kangojimu@mars.ihs.u-tokai.ac.jp","添付書類":"1.2014履歴書様式（配布用）.xls","Web応募":"不可"}}