{"time":"2014-10-07 00:00:00 -0700","subject":"講師または准教授の公募（保育学）","period":"2014年10月03日 ～,2014年11月14日 消印有効","place":["愛媛県"],"place_en":["Ehime"],"genre":"社会科学","institution":"松山東雲短期大学","title":"准教授・常勤専任講師相当","id":"D114100482","data":{"データ番号":"D114100482","公開開始日":"2014年10月07日","更新日":"2014年10月07日","求人件名":"講師または准教授の公募（保育学）","機関名":"松山東雲短期大学","機関または部署":"http://www.shinonome.ac.jp","部署名":"保育科","機関種別":"短期大学","求人内容":"<div class=\"margin-01\">[機関の説明(募集の背景、機関の詳細、プロジェクトの説明等)]<br><br><br>[仕事内容(業務内容、担当科目等)]<br>担当科目：<br>【保育科専門科目】<br>　保育原理、家庭支援論、保育相談演習、保育実習指導Ⅰ、保育実習指導Ⅱ、教育実習Ⅰ、教育実習Ⅱ、保育ゼミナールⅠ、保育ゼミナールⅡ、保育総合演習など<br><br>[勤務地住所等]<br>790-8531　愛媛県松山市桑原3丁目2番1号<br><br>[募集人員]<br>1名<br>講師、または准教授　（専任かつ常勤） <br><br>[着任時期]<br>2015年04月01日<br><br>,</div>","研究分野":"社会科学","            小分類":"教育学","職種":"\r\n            \r\n            准教授・常勤専任講師相当\r\n            \r\n            ","":"准教授・常勤専任講師相当","勤務形態":"常勤（任期あり）,1年契約の4年任期","勤務地":"四国 -,愛媛県","応募資格":"（1）大学院修士課程修了以上、またはそれと同等以上の業績（研究歴あるいは専門職歴）をもつ者。（2）本学はキリスト教の精神に基づく教育機関であるので、クリスチャン、あるいはキリスト教に理解のある者。","待遇":"給与は本学給与規程に拠る（定年制教員と同様）","募集期間":"2014年10月03日 ～,2014年11月14日 消印有効","応募・選考・結果通知・連絡先":"[応募方法(書類送付先も含む)]（1）履歴書（所定の様式）（2）教育研究業績書（所定の様式）（3）主要な教育研究業績を3点（抜き刷り、コピーでも可、それぞれ800字程度の要旨を付けること）  なお、選考開始後に、上記以外の研究業績その他の送付を依頼することもある。（4）推薦者がいる場合は、推薦書も添付する。[選考内容(選考方法、採否の決定)、結果通知方法]第1次審査：書類選考第2次審査：面接およびプレゼンテーション[連絡先(担当者所属、役職、氏名、e-mail、電話番号)] ※重要〒790—8531　愛媛県松山市桑原３丁目２番１号松山東雲短期大学　保育科長　児嶋　雅典　宛電話０８９−９３１−６２１１（内線４１９）Fax０８９—９３３−５５５９E-mail mkojima@shinonome.ac.jp※ 封筒に「教員応募書類」と朱書きし、郵送の場合は書留郵便にする。","添付書類":"1.教育研究業績書.doc,2.履歴書.doc","備考":"（1）結果については12月5日(金)までに本人に通知する。（2）提出書類は原則として返却しない。（3）面接時の交通費・宿泊費は自己負担とする。","Web応募":"不可"}}