{"time":"2014-09-08 00:00:00 -0700","subject":"横浜国立大学大学院都市イノベーション研究院教員公募（建築史・建築理論分野准教授）","period":"2014-09-08:2014-10-31:NA","place":["神奈川県"],"place_en":["Kanagawa"],"genre":"工学","institution":"横浜国立大学","title":"准教授・常勤専任講師相当","id":"D114090246","data":{"データ番号":"D114090246","公開開始日":"2014年09月08日","更新日":"2014年09月08日","求人件名":"横浜国立大学大学院都市イノベーション研究院教員公募（建築史・建築理論分野准教授）","機関名":"横浜国立大学","機関または部署":"http://www.urban.ynu.ac.jp/","部署名":"大学院都市イノベーション研究院","機関種別":"国立大学","公募の":"http://www.ynu.ac.jp/hus/urban/12194/detail.html","求人内容":"<div class=\"margin-01\">[機関の説明(募集の背景、機関の詳細、プロジェクトの説明等)]<br>募集人員：准教授１名<br><br>所属：大学院都市イノベーション研究院<br>担当：大学院都市イノベーション学府<br>兼務：理工学部建築都市・環境系学科建築教育プログラム<br>兼務：工学部建設学科<br><br>[仕事内容(業務内容、担当科目等)]<br>１）大学院都市イノベーション学府での、(仮称)建築史・建築理論(前期科目)、 (仮称)建築史・建築理論特論(後期科目)、建築理論スタジオおよび関連科目（博士課程前期・博士課程後期）<br>２）理工学部/工学部での専門科目（近代建築史、西洋建築史、建築史演習、デザインスタジオなど）および関連科目（英語講義科目含む）<br><br>＊その他必要とされる教育・指導・研究および学内諸業務も担当する。なお、学部・大学院それぞれのカリキュラム改革等の理由により、上記以外の授業を担当していただくこともあります。<br><br>[勤務地住所等]<br>神奈川県横浜市保土ケ谷区常盤台79-5<br><br>[募集人員]<br>1名<br>准教授<br><br>[着任時期]<br>2015年04月01日<br><br>,</div>","研究分野":"工学","            小分類":"土木工学","職種":"\r\n            \r\n            准教授・常勤専任講師相当\r\n            \r\n            ","":"准教授・常勤専任講師相当","勤務形態":"常勤（任期なし）,ただし、定年は65歳","勤務地":"関東 -,神奈川県","応募資格":"１）担当授業分野に関する専門的知識/経験があること。２）博士の学位を有するか、それに相当する研究業績があること。３）日本語を母語としない場合、職務上必要な程度の日本語運用能力があること。","募集期間":"2014年09月08日 ～,2014年10月31日 必着","応募・選考・結果通知・連絡先":"[応募方法(書類送付先も含む)]【応募書類】１）履歴書　1通２）教育研究業績書　1通３）主要研究業績　3編４）３）の主要研究業績の概要（400字程度）　各1部５）これまでの教育および研究の概要と着任後の研究計画（それぞれA4用紙1枚）【応募書類送付先】〒240-8501　横浜市保土ケ谷区常盤台79-5横浜国立大学都市イノベーション学府事務室　総務係提出書類を一括して取り揃え、封筒に朱書きで「建築史・建築理論分野公募書類在中」と明記のうえ、書留で郵送願います。なお、提出書類は原則として返却しません。返却をご希望の方は返却用の封筒に切手を添付し、返却先住所氏名を記入して同封してください。[選考内容(選考方法、採否の決定)、結果通知方法]書類審査。必要に応じて面接を実施することがあります。その場合の交通費等は応募者の負担とします。[連絡先(担当者所属、役職、氏名、e-mail、電話番号)] ※重要横浜国立大学大学院都市イノベーション研究院　教授　高見沢実e-mail:takamiz[at]ynu.ac.jp（お手数ですが、メールアドレスは[at]の箇所を@に置き換えてご使用ください。）","添付書類":"1.rirekisyo.doc,2.gyousekisyo.doc","備考":"提出書類は選考に係る審査のみに利用し、本学の規則に基づき適切に管理します。本学では、女性の方及び海外での教育・研究経験者の応募を歓迎いたします。","Web応募":"不可"}}