{"time":"2015-04-27 00:00:00 +0900","subject":"専任教員の公募（保健体育科教育学）","period":"2015-04-23:2015-06-04:NA","place":["福岡県"],"place_en":["Fukuoka"],"genre":"複合領域","institution":"福岡大学","title":"教授相当:准教授・常勤専任講師相当","id":"D115041015","data":{"データ番号":"D115041015","公開開始日":"2015年04月25日","更新日":"2015年04月27日","求人件名":"専任教員の公募（保健体育科教育学）","機関名":"福岡大学","部署名":"スポーツ科学部　","機関種別":"私立大学","求人内容":"<div class=\"margin-01\"><p style=\"word-wrap: break-word;\">このたび本学部では下記の要領により教員の公募をすることになりました。<br><br>[仕事内容(業務内容、担当科目等)]<br>担当科目：保健体育科教育法、教職事前実習、保健体育教職演習、教育実習事前・事後指導<br><br><br>[募集人員]<br>1名<br>講師以上<br><br><br>[着任時期]<br>2016年04月01日<br><br></p></div>","研究分野":"複合領域","            小分類":"健康・スポーツ科学","職種":"\r\n            \r\n            教授相当\r\n            \r\n            :\r\n            \r\n            准教授・常勤専任講師相当\r\n            \r\n            ","":"准教授・常勤専任講師相当","勤務形態":"常勤（任期なし）","勤務地":"九州・沖縄 -,福岡県","応募資格":"（1）修士以上の学位を有すること、又はそれと同等の能力を有すること（2）大学院を担当できることが望ましい（3）平成28年4月1日に就任できること","待遇":"職名：教授・准教授・専任講師相当","募集期間":"2015年04月23日 ～,2015年06月04日 必着","応募・選考・結果通知・連絡先":"[応募方法(書類送付先も含む)]（1）履歴書　　（※別紙①）　　※本学指定（2）教育業績書（※別紙②）（3）職務実績書（※別紙③）（4）研究業績書（※別紙④）     研究業績書に記載した全ての著書、学術論文等の現物、抜刷、又は写し（5）競技歴及び指導歴（※別紙⑤）〒814-0180福岡市城南区七隈8-19-1福岡大学スポーツ科学部長宛（封筒に「教員応募書類在中」と朱書し書留郵便で郵送すること）一次選考：書類審査二次選考：平成27年7月1日（水）16：30～　　　　　面接・専門に関するプレゼンテーション（20分間）　　　　　※旅費等の支給はありません。814-0180福岡県 福岡市城南区七隈8-19-1福岡大学スポーツ科学部長田中　守TEL:092-871-6631FAX:092-865-6029","添付書類":"1.教員公募所定様式.docx,2.教員公募所定様式　記入例.doc","備考":"保健体育科教育法、教職事前実習、保健体育教職演習、教育実習事前・事後指導・福岡大学は男女共同参画を推進しています。","Web応募":"不可"}}