{"time":"2015-03-21 00:00:00 +0900","subject":"放射線医学教室，教員（講師・助教）募集","period":"2015-03-20:2015-09-30:採用が決定次第，締切ます。","place":["滋賀県 京都府 大阪府 兵庫県"],"place_en":[null],"genre":"医歯薬学:医歯薬学:医歯薬学","institution":"京都府立医科大学","title":"准教授・常勤専任講師相当:助教相当","id":"D115030663","data":{"データ番号":"D115030663","公開開始日":"2015年03月21日","更新日":"2015年03月21日","求人件名":"放射線医学教室，教員（講師・助教）募集","機関名":"京都府立医科大学","機関または部署":"http://www.f.kpu-m.ac.jp/k/radiol/","部署名":"放射線科","機関種別":"公立大学","求人内容":"<div class=\"margin-01\"><p style=\"word-wrap: break-word;\">[機関の説明(募集の背景、機関の詳細、プロジェクトの説明等)]<br><br>放射線治療ないし画像診断領域における医師を広く募集<br>陽子線センターを運営するにあたり医学物理士を募集<br><br>[仕事内容(業務内容、担当科目等)]<br><br>放射線医学<br>医学物理<br><br>[勤務地住所等]<br><br>京都府立医大及び関連施設<br>http://www.f.kpu-m.ac.jp/k/radiol/training_guide/hospital.html<br><br>[募集人員]<br><br>画像診断医 2名<br>放射線治療医 2名<br>医学物理士 2名<br><br>[着任時期]<br><br>未定<br><br></p></div>","研究分野":"医歯薬学:医歯薬学:医歯薬学","            小分類":"医学物理","職種":"\r\n            \r\n            准教授・常勤専任講師相当\r\n            \r\n            :\r\n            \r\n            助教相当\r\n            \r\n            ","":"助教相当","勤務形態":"常勤（任期あり）","勤務地":"近畿 -,滋賀県 京都府 大阪府 兵庫県","応募資格":"応相談放射線科専門医医学物理士","待遇":"週5日間勤務（土曜日および日曜日は当直オンコール以外は休み）","募集期間":"2015年03月20日 ～,2015年09月30日 必着,採用が決定次第，締切ます。","応募・選考・結果通知・連絡先":"[応募方法(書類送付先も含む)]応募の方は医局長にEメールで問い合わせください。その後、履歴書等をご送付いただきます。[連絡先(担当者所属、役職、氏名、e-mail、電話番号)] ※重要医局長　松島成典 matsu@koto.kpu-m.ac.jp","Web応募":"不可","機関紹介サイト":"当該機関の外部サイト情報を新規ウィンドウで表示します。"}}