{"time":"2014-12-26 00:00:00 -0800","subject":"「助教の公募（成人看護学分野）」","period":"2014-12-26:2015-03-31:NA","place":["北海道"],"place_en":["Hokkaido"],"genre":"医歯薬学","institution":"札幌保健医療大学","title":"助教相当","id":"D114121563","data":{"データ番号":"D114121563","公開開始日":"2014年12月26日","更新日":"2014年12月26日","求人件名":"「助教の公募（成人看護学分野）」","機関名":"札幌保健医療大学","機関または部署":"http://www.sapporo-hokeniryou-u.ac.jp/","部署名":"事務局","機関種別":"私立大学","求人内容":"<div class=\"margin-01\"><p style=\"word-wrap: break-word;\">[機関の説明(募集の背景、機関の詳細、プロジェクトの説明等)]<br><br><br>[仕事内容(業務内容、担当科目等)]<br>　講義および演習担当<br><br>　成人看護活動論Ⅱ、成人看護活動論Ⅲ、成人看護実習Ⅱ、看護基礎実習Ⅰ、看護基礎実習Ⅱ、看護総合実習、実践総合演習<br><br><br><br>[勤務地住所等]<br>北海道札幌市東区中沼西４条２丁目１番１５号<br><br>[募集人員]<br>1名<br>助教<br><br>[着任時期]<br>2015年10月01日<br><br></p></div>","研究分野":"医歯薬学","            小分類":"看護学","職種":"\r\n            \r\n            助教相当\r\n            \r\n            ","":"助教相当","勤務形態":"常勤（任期なし）","勤務地":"北海道 -,北海道","応募資格":"　大学院修士課程（看護学）を修了した者（修了見込みの者を含む）で、看護師免許を有し、原則として５年以上の臨床経験を有する者。なお、大学院博士課程を修了した者（修了見込みの者を含む）が望ましい。　※　本学は大学設置計画進行中のため、提出書類は文部科学省の大学設置・学校法人審議会の専門委員会による教員資格審査に申請します。　　　正式採用にあたっては、文部科学省の大学設置・学校法人審議会の専門委員会による教員資格審査において、「適格」と判定されることが前提条件となります。","待遇":"　学園の規程による。　問い合わせには応じます。","募集期間":"2014年12月26日 ～,2015年03月31日 必着","応募・選考・結果通知・連絡先":"[応募方法(書類送付先も含む)]　（１）個人調書（履歴書）および教育研究業績書（本学所定様　　　　式）　（２）最近５年間の主要業績の現物またはコピー　３編以内（返　　　却します）　　※　１．書類は簡易書留で郵送してください。　　　　２．本学所定様式は、本学のホームページからダウンロー　　　　　ドしてください。　[選考内容(選考方法、採否の決定)、結果通知方法]　第１次　書類審査　第２次　面　　接　※　面接に係る旅費等は支給しません。[連絡先(担当者所属、役職、氏名、e-mail、電話番号)] ※重要　〒００７－０８９４　　札幌市東区中沼西４条２丁目１番１５号　　　札幌保健医療大学　事務局　　　　担当　久保、照井　　　ＴＥＬ　０１１－７９２－３３５０　　　ＦＡＸ　０１１－７９２－３３５８","Web応募":"不可"}}