{"time":"2015-01-27 00:00:00 -0800","subject":"教員の公募（機械工学科・熱力学分野）","period":"2015-01-26:2015-02-27:NA","place":["秋田県"],"place_en":["Akita"],"genre":"工学","institution":"秋田工業高等専門学校","title":"教授相当:准教授・常勤専任講師相当:助教相当","id":"D115011222","data":{"データ番号":"D115011222","公開開始日":"2015年01月27日","更新日":"2015年01月27日","求人件名":"教員の公募（機械工学科・熱力学分野）","機関名":"秋田工業高等専門学校","機関または部署":"http://www.ipc.akita-nct.ac.jp/b03/b03_02.html","部署名":"機械工学科","機関種別":"高等専門学校","公募の":"http://www.ipc.akita-nct.ac.jp/b13/b13_01.html","求人内容":"<div class=\"margin-01\"><p style=\"word-wrap: break-word;\">1.職名・人員　教授，准教授または助教・１名<br>2.所属学科等　機械工学科<br>3.専門分野　　熱力学分野<br>4.担当科目<br>　工業熱力学，熱工学，伝熱工学，工学実験，工学特別実験，基礎研究，卒業研究，特別研究等<br>5.採用予定日　平成２７年５月１日<br>※ 本校では，他高専等との人事交流を行うため，採用後，原則として他高専等との間で１～３年程度の交流人事を行う予定になっております。<br>※ 本校では，英語授業講義力強化を推進しております。</p></div>","研究分野":"工学","            小分類":"機械工学","職種":"\r\n            \r\n            教授相当\r\n            \r\n            :\r\n            \r\n            准教授・常勤専任講師相当\r\n            \r\n            :\r\n            \r\n            助教相当\r\n            \r\n            ","":"助教相当","勤務形態":"常勤（任期なし）","勤務地":"東北 -,秋田県","応募資格":"1.博士の学位を有する方2.心身ともに健康で，高等専門学校における教育・研究に関心を持ち，クラス担任，クラブ指導および学生寮の学生指導等に理解と熱意を持っている方3.独立行政法人国立高等専門学校機構秋田工業高等専門学校は男女共同参画を推進しており，業績（教育業績，研究業績，社会的貢献，人物を含む。）の評価において同等と認められる場合には，女性を優先的に採用します。","待遇":"独立行政法人国立高等専門学校機構教職員就業規則による。","募集期間":"2015年01月26日 ～,2015年02月27日 必着","応募・選考・結果通知・連絡先":"1.応募書類：(1)履歴書（市販の用紙に本人自筆，写真貼付，E-mailアドレス記載のこと）(2)個人調書･･･所定の様式（第１号様式）(3)著書・論文等一覧（論文，著書，口頭発表，教育機関研究発表，特許，実務実績，各種資格等を項目別に記載）･･･所定の様式（第２号様式）(4)主要論文（５編以内）の別刷り（各１部，コピー可）とその概略（各800字程度）･･･所定の様式（第３号様式）(5)着任後の教育・研究についての抱負（A4版用紙に1,000字程度にまとめたもの）(6)推薦書（様式任意）又は応募者について参考意見を聞くことができる者の氏名と連絡先「所定の様式」については，本校ホームページ（http://akita-nct.jp/b13/b13_01.html）の教職員採用案内から取得のうえ，作成願います。2.書類提出先：〒011-8511 秋田県秋田市飯島文京町１番１号秋田工業高等専門学校総務課人事係※ 郵送の場合は「書留」とし，封筒に「機械工学科教員応募書類在中」と朱書きすること。なお，応募書類は原則として返却いたしません。3.応募期限：平成２７年２月２７日（金）（必着）4.選考方法：第一次選考　書類審査第二次選考　第一次合格者を対象とした面接（面接予定時期：平成27年3月頃）5.問い合わせ先：秋田工業高等専門学校　機械工学科長　若生　昌光E-mail:wakoh-m@akita-nct.ac.jpTel:018-847-6034Fax:018-857-3191","備考":"上記の担当者に連絡が取れない場合は総務課人事係（下記）へ　TEL:018-847-6006　FAX:018-857-3191","Web応募":"不可"}}