{"time":"2015-01-24 00:00:00 -0800","subject":"北海道大学大学院理学研究院化学部門教員公募","period":"NA:2015-03-31:NA","place":["北海道"],"place_en":["Hokkaido"],"genre":"複合領域","institution":"北海道大学","title":"准教授・常勤専任講師相当","id":"D115011104","data":{"データ番号":"D115011104","公開開始日":"2015年01月24日","更新日":"2015年01月24日","求人件名":"北海道大学大学院理学研究院化学部門教員公募","機関名":"北海道大学","機関または部署":"http://wwwchem.sci.hokudai.ac.jp/","部署名":"理学研究院・化学部門","機関種別":"国立大学","公募の":"http://wwwchem.sci.hokudai.ac.jp/","求人内容":"<div class=\"margin-01\"><p style=\"word-wrap: break-word;\">[機関の説明(募集の背景、機関の詳細、プロジェクトの説明等)]<br><br><br>[仕事内容(業務内容、担当科目等)]<br><br>天然物化学・ケミカルバイオロジー：天然物の合成および生合成に関する研究、遺伝子操作を駆使して新規酵素の反応機構を解析し、有機合成への適用を目指す研究<br>（なお研究は、及川英秋教授と協力して行なう）<br><br>[勤務地住所等]<br>060-0810<br>北海道 札幌市北区北１０条西８丁目<br><br><br>[募集人員]<br><br>准教授または講師　１名<br><br>[着任時期]<br><br>決定後，なるべく早い時期</p></div>","研究分野":"複合領域","            小分類":"生体分子科学","職種":"\r\n            \r\n            准教授・常勤専任講師相当\r\n            \r\n            ","":"准教授・常勤専任講師相当","勤務形態":"常勤（任期なし）","勤務地":"北海道 -,北海道","応募資格":"博士の学位を有し、大学院・学部の教育研究を担当できる方","待遇":"大学の規定による。","募集期間":"2015年03月31日 必着","応募・選考・結果通知・連絡先":"[応募方法(書類送付先も含む)](1) 履歴書（写真添付、2部）(2) 業績リスト（2部レフェリー制のある学術論文とその他に分けること） (3) 主要論文の別刷7編以内（各2部）(4) これまでの研究の概要（2000字程度）と今後の研究計画および教育に対する抱負（まとめて1000字程度）（各2部）(5) 所見を求め得る方2名の氏名と連絡先（2部）(6) 参考資料（最近の研究費取得状況、受賞歴、国際学会発表歴等）（2部）応募書類の送付先:〒060-0810 札幌市北区北１０条西８丁目北海道大学大学院理学研究院化学部門人事選考委員会委員長　村上　洋太[選考内容(選考方法、採否の決定)、結果通知方法][連絡先(担当者所属、役職、氏名、e-mail、電話番号)] ※重要公募に関する問合せ先:北海道大学大学院理学研究院化学部門有機反応論研究室　及川 英秋Tel: 011-706-2622; Fax: 011-706-3448hoik@sci.hokudai.ac.jp（具体的な応募情報は、記載したURLで確かめられます）応募書類の返却は致しません。","Web応募":"不可"}}