{"time":"2015-02-11 00:00:00 -0800","subject":"成人看護学領域　准教授または講師の公募","period":"2015年04月30日 消印有効,採用者が決定次第、公募を終了します。","place":["神奈川県"],"place_en":["Kanagawa"],"genre":"医歯薬学","institution":"横浜創英大学","title":"准教授・常勤専任講師相当","id":"D115020394","data":{"データ番号":"D115020394","公開開始日":"2015年02月11日","更新日":"2015年02月11日","求人件名":"成人看護学領域　准教授または講師の公募","機関名":"横浜創英大学","部署名":"総務部","機関種別":"私立大学","求人内容":"<div class=\"margin-01\"><p style=\"word-wrap: break-word;\">[担当科目]<br>成人看護学方法論Ⅰ/成人看護学方法論Ⅱ/成人看護学方法論Ⅲ/成人看護学方法論Ⅳ/成人看護学実習（慢性期）/成人看護学実習（急性期）<br><br>[勤務地住所]<br>〒226-0015<br>神奈川県横浜市緑区三保町1番地<br><br>[募集人員]<br>2名<br><br>[着任時期]<br>2015年4月<br></p></div>","研究分野":"医歯薬学","            小分類":"看護学","職種":"\r\n            \r\n            准教授・常勤専任講師相当\r\n            \r\n            ","":"准教授・常勤専任講師相当","勤務形態":"常勤（任期なし）","勤務地":"関東 -,神奈川県","応募資格":"看護師の資格を有し、次の各号の条件を満たす者1.修士の学位を有する者（取得見込みを含む）2.研究発表等の業績がある者3.臨地での経験を3年以上積んでいる者","待遇":"[職　　名]　准教授又は講師[給　　与]　本学給与規程に準ずる（詳しくはお問合せください）[勤務時間]　月～金　9：00～17：00[休　　日]　日曜・祝日[保 険 等]　社会保険等完備","募集期間":"2015年04月30日 消印有効,採用者が決定次第、公募を終了します。","応募・選考・結果通知・連絡先":"[提出書類]・履歴書・教育業績がある場合は、別途添付。[応募方法]・郵送・Web公募　「可」です。[選考方法]・書類選考及び面接[連絡先及び送付先]〒226-0015神奈川県横浜市緑区三保町1番地総務課　鈴木TEL:045-922-5641（代表）E-mail:swift@soei.ac.jp公募書類の返却は、原則返却しません。","Web応募":"可","機関紹介サイト":"当該機関の外部サイト情報を新規ウィンドウで表示します。"}}