{"time":"2015-02-10 00:00:00 -0800","subject":"九州大学サマーコース 日本語非常勤講師募集","period":"NA:2015-02-27:NA","place":["福岡県"],"place_en":["Fukuoka"],"genre":"人文学","institution":"九州大学","title":"非常勤講師相当","id":"D115020396","data":{"データ番号":"D115020396","公開開始日":"2015年02月10日","更新日":"2015年02月10日","求人件名":"九州大学サマーコース 日本語非常勤講師募集","機関名":"九州大学","機関または部署":"http://www.isc.kyushu-u.ac.jp/center/home.htm","部署名":"国際交流推進室","機関種別":"国立大学","公募の":"http://www.isc.kyushu-u.ac.jp/atw/","求人内容":"<div class=\"margin-01\"><p style=\"word-wrap: break-word;\">[機関の説明(募集の背景、機関の詳細、プロジェクトの説明等)]<br>本学箱崎キャンパスで開講されるサマーコースに参加する留学生向けの日本語の授業を担当して下さる方を募集いたします。<br><br>[仕事内容(業務内容、担当科目等)]<br>担当科目： 日本語 （初級〜上級）<br><br>任期・人員：下記のいずれかの期間、もしくは全期間（前期・後期）を通して教えられる方<br>• 前期のみ（6月29日〜7月14日） 若干名<br>• 後期のみ（7月21日〜8月5日） 若干名<br><br>※ 担当授業時間は最大（＝全期間）で60時間 (予定) です。<br>※ 全期間希望の場合でも、前期・後期のいずれかのみとなることがありますので、ご了承ください。<br><br>[勤務地住所等]<br>福岡市東区箱崎6-10-1<br><br>[着任時期]<br>2015年06月29日　または、2015年7月21日から<br></p></div>","研究分野":"人文学","            小分類":"日本語教育","職種":"\r\n            \r\n            非常勤講師相当\r\n            \r\n            ","":"非常勤講師相当","勤務形態":"非常勤（任期あり）","勤務地":"九州・沖縄 -,福岡県","応募資格":"1. 4年制大学卒業以上の学歴を有する方2. 大学生を対象とした外国語としての日本語教育の教授経験が4年以上ある方 （プライベートレッスンやTAとしての経験は除く）3. 英語の運用能力が必要十分にある方","待遇":"1. 謝金額は九州大学の日本語非常勤講師謝金規定により決定します。2. 通勤交通費、及び宿泊費は支給されません.","募集期間":"2015年02月27日 必着","応募・選考・結果通知・連絡先":"[応募方法(書類送付先も含む)]1. 履歴書（http://www.isc.kyushu-u.ac.jp/atw/Rireki-15.doc）2. 日本語教育の実績・研究業績（http://www.isc.kyushu-u.ac.jp/atw/form2-3.doc）3. 授業風景の録画映像※ 1, 2は、本学所定の様式をダウンロードし記入要領に従って作成すること。※ 「3. 授業風景の録画映像」については、 30分以内で音声・映像の明瞭なものを PCもしくはMacで再生可能なメディアで送付すること。[選考内容(選考方法、採否の決定)、結果通知方法]・締切を過ぎての応募は受け付けられませんのでご注意ください。・採用・不採用については3月中に通知します。・書類選考通過者には面接・模擬授業を実施する場合があります。[連絡先(担当者所属、役職、氏名、e-mail、電話番号)] ※重要〒812-8581福岡市東区箱崎6-10-1 九州大学国際交流推進室 (担当:高原)","添付書類":"1.Japaneselecturers-2.pdf","備考":"封筒の表に朱書きで「夏期日本語非常勤講師応募書類」と明記のこと。 応募書類は原則として返却しません。","Web応募":"不可","機関紹介サイト":"当該機関の外部サイト情報を新規ウィンドウで表示します。"}}