{"time":"2015-02-06 00:00:00 -0800","subject":"基礎看護学分野担当教員（助教または助手）の公募","period":"2015-02-05:2015-03-02:NA","place":["山口県"],"place_en":["Yamaguchi"],"genre":"医歯薬学","institution":"山口大学","title":"助教相当:研究・教育補助者相当","id":"D115020250","data":{"データ番号":"D115020250","公開開始日":"2015年02月06日","更新日":"2015年02月06日","求人件名":"基礎看護学分野担当教員（助教または助手）の公募","機関名":"山口大学","機関または部署":"http://www.med.yamaguchi-u.ac.jp/","部署名":"大学院医学系研究科保健学系学域基礎看護学分野","機関種別":"国立大学","求人内容":"<div class=\"margin-01\"><p style=\"word-wrap: break-word;\">山口大学大学院医学系研究科では，保健学系学域　基礎看護学分野担当教員（助教または助手）の募集をすることになりました。<br><br>担当予定科目<br>（助教）<br>　看護過程論，基礎看護方法論Ⅰ，基礎看護方法論Ⅱ，基礎看護方法演習Ⅰ，基礎看護方法演習Ⅱ，基礎看護学実習Ⅰ，基礎看護学実習Ⅱ，看護学卒業研究，共通教育科目（社会と医療）<br><br>（助手）<br>　看護過程論（演習），基礎看護方法演習Ⅰ，基礎看護方法演習Ⅱ，基礎看護学実習Ⅰ，基礎看護学実習Ⅱ<br><br>[勤務地住所等]<br>山口県宇部市南小串１丁目１番１号<br><br>[募集人員]<br>1名<br>助教または助手<br><br>[着任時期]<br>2015年04月01日</p></div>","研究分野":"医歯薬学","            小分類":"看護学","職種":"\r\n            \r\n            助教相当\r\n            \r\n            :\r\n            \r\n            研究・教育補助者相当\r\n            \r\n            ","":"研究・教育補助者相当","勤務形態":"常勤（任期あり）,採用日から５年（２回限り再任可）","勤務地":"中国 -,山口県","応募資格":"（１）山口大学における教育・研究に情熱をもって取り組める方（２）看護師免許を有すること（３）３年以上の実務経験を有すること（４）助教は修士の学位を有すること　　　助手の場合は学士の学位を有すること","待遇":"職名：助教または助手","募集期間":"2015年02月05日 ～,2015年03月02日 必着","応募・選考・結果通知・連絡先":"[応募方法(書類送付先も含む)](1)履歴書（指定様式　右肩に写真を添付）1通　(2)教育・研究業績（指定様式）　　　　　1部(3)看護師免許の写し　　　　　　　　　　1通(4)これまでの研究活動の概略と今後の研究の抱負（1200字程度）　　　　　　　　　　　　　　　　　　1部(5)教育に対する今後の抱負（1200字程度）1部(6)推薦状（未開封のもの）　　　　  　　1通(7)その他（連絡先と連絡方法についてお書き下さい。書式は自由です。）応募書類は返却いたしません。応募書類により取得する個人情報は，採用者の選考及び任用の手続きに利用するものであり，この目的以外で利用及び提供することはありません。送付先：〒755-8505山口県宇部市南小串１丁目１番１号　　　山口大学医学部総務課人事係　問い合わせ先：〒755-8505山口県宇部市南小串１丁目１番１号　　　山口大学大学院医学系研究科保健学系学域基礎看護学分野　　　　　　　 藤澤怜子TEL/FAX： 0836-22-2814　　E-mail：　reiko@yamaguchi-u.ac.jp","添付書類":"1.1公募文書(基礎看護)2015.2.pdf,2.2教員公募書類作成上の注意事項.pdf,3.3履歴書.doc,4.4履歴書記入例.pdf,5.5教育研究業績.doc,6.6教育研究業績記入例.pdf","備考":"・郵送の場合は書留とし、封筒の表に「基礎看護学分野教員応募書類在中」と朱記のこと。・選考にあたって、面接等を実施します。・本学では5年間の任期制をとっています。詳しいことは、お問い合わせ下さい。","Web応募":"不可"}}