{"time":"2015-01-28 00:00:00 -0800","subject":"技術員の公募（資源化学研究所・生物資源部門）","period":"2015-01-26:2015-02-18:NA","place":["神奈川県"],"place_en":["Kanagawa"],"genre":"生物学","institution":"東京工業大学","title":"研究・教育補助者相当","id":"D115011238","data":{"データ番号":"D115011238","公開開始日":"2015年01月28日","更新日":"2015年01月28日","求人件名":"技術員の公募（資源化学研究所・生物資源部門）","機関名":"東京工業大学","機関または部署":"http://www.res.titech.ac.jp/index.html","部署名":"資源化学研究所","機関種別":"国立大学","公募の":"http://www.hyoka.koho.titech.ac.jp/eprd/recently/koubo/koubo.php","求人内容":"<div class=\"margin-01\"><p style=\"word-wrap: break-word;\">資源化学研究所生物資源部門では、分子生物学実験を補佐して下さる技術員１名を募集致します。<br><br>[仕事内容]<br>分子生物学実験（クローニング、ウェスタン解析、ノザン解析、リアルタイムPCR解析、電気泳動など）に関する技術補助業務<br><br>[勤務地住所等]<br>横浜市緑区長津田町4259番地<br>資源化学研究所<br><br>[募集人員]<br>１名<br><br>[着任時期]<br>２０１５年４月１日</p></div>","研究分野":"生物学","            小分類":"全て","職種":"\r\n            \r\n            研究・教育補助者相当\r\n            \r\n            ","":"研究・教育補助者相当","勤務形態":"非常勤（任期あり）,最長で平成２９年３月３１日","勤務地":"関東 -,神奈川県","応募資格":"・ウェスタン解析、ノザン解析、リアルタイムPCR解析の経験のある方・組換えタンパク質の発現・精製経験のある方","待遇":"①１週間の通常勤務時間　火：　10:15～16:15 (5時間)　水：　10:15～16:15 (5時間)　木：　10:15～16:15 (5時間)　金：　10:15～16:15 (5時間)上記の曜日と時間を基本としますが、曜日・時間については応相談休憩時間は12:15〜13:15となります②超過勤務：無③休日：土曜，日曜，祝日，年末年始(12/29～1/3)④有給休暇及びその他の休暇制度あり⑤年俸　月額89,000円～108,000円（各種手当含む）⑥保険：雇用保険,労働者災害補償保険","募集期間":"2015年01月26日 ～,2015年02月18日 必着","応募・選考・結果通知・連絡先":"[応募方法]①応募書類：履歴書（写真貼付、これまでの実験経験を具体的に記載下さい）＊応募書類は返却しません。＊本学での勤務経験がある場合は、所属していた部署名や従事していた研究室名まで詳しくご記入をお願いします。②送付先：〒226-8503　横浜市緑区長津田町4259番地　R1-32　　　　　　国立大学法人東京工業大学すずかけ台地区事務部　　　　　　総務課総務・研究所事務グループ　　　　　　（資源化学研究所事務室）＊封筒に｢資源化学研究所 田中・今村研究室応募書類在中｣と朱書してください。[選考内容(選考方法）]第１次　：　書類選考第２次　：　面接試験＊第１試験合格者のみ，前日までに時間・場所等を通知します＊面接試験を受けた方には、３月１０日までに選考結果を通知致します。[問い合わせ先] 氏名：今村　壮輔　　　 E-mail: simamura@res.titech.ac.jpTEL ：045-924-5859    Fax ：045-924-5859","Web応募":"不可"}}