{"time":"2015-01-20 00:00:00 -0800","subject":"非常勤講師の公募（臨床医学神経内科）","period":"NA:2015-02-16:NA","place":["埼玉県"],"place_en":["Saitama"],"genre":"医歯薬学","institution":"文京学院大学","title":"非常勤講師相当","id":"D115010767","data":{"データ番号":"D115010767","公開開始日":"2015年01月20日","更新日":"2015年01月20日","求人件名":"非常勤講師の公募（臨床医学神経内科）","機関名":"文京学院大学","部署名":"保健医療技術学部","機関種別":"私立大学","求人内容":"<div class=\"margin-01\"><p style=\"word-wrap: break-word;\">[機関の説明(募集の背景、機関の詳細、プロジェクトの説明等)]<br>欠員教員の補充<br><br>[仕事内容(業務内容、担当科目等)]<br>公募職種：文京学院大学　非常勤講師<br>担当授業科目：臨床医学神経内科Ⅰ･Ⅱ（半期各1コマ）2年次配当<br><br>[勤務地住所等]<br>埼玉県ふじみ野市亀久保１１９６<br>ふじみ野キャンパス<br><br>[募集人員]<br>1名<br>非常勤講師<br><br>[着任時期]<br>2015年04月01日<br><br></p></div>","研究分野":"医歯薬学","            小分類":"内科系臨床医学","職種":"\r\n            \r\n            非常勤講師相当\r\n            \r\n            ","":"非常勤講師相当","勤務形態":"非常勤（任期あり）","勤務地":"関東 -,埼玉県","応募資格":"(1)医師免許を有していること。(2)5年以上の臨床経験を有していること。(3)教育機関等での教育・研究経験を有することが望ましい。","待遇":"職位、業績等を考慮の上、決定します。その他勤務条件は、文京学院大学非常勤講師就業規則による。","募集期間":"2015年02月16日 必着","応募・選考・結果通知・連絡先":"[応募方法(書類送付先も含む)](1)個人調書　1通（本学所定の様式）(2)教育研究業績書　1通（本学所定の様式）(3)取得学位と各種免許状の保持者は、その複写又はそれを証明する文書[選考内容(選考方法、採否の決定)、結果通知方法](1)書類審査による選考(2)（書類審査通過者のみ）面接による選考（※面接日時等は追ってご連絡いたします。）[連絡先(担当者所属、役職、氏名、e-mail、電話番号)] ※重要356-8533埼玉県ふじみ野市亀久保１１９６文京学院大学　保健医療技術学部・教務グループ気付「保健医療技術学部長」宛","添付書類":"1.履歴書.doc,2.教育研究業績書.doc,3.記入例（履歴書）.pdf,4.記入例（教育研究業績書）.pdf","備考":"※郵送は、封書に「臨床医学神経内科Ⅰ･Ⅱ 非常勤講師応募書類在中」と朱書きし、書留又は簡易書留にて期限内に必着するようにご送付ください。","Web応募":"不可"}}