{"time":"2015-02-03 00:00:00 -0800","subject":"東海中学校・高等学校 音楽科 非常勤講師募集","period":"NA:2015-02-19:終了日前に採用者を決定する可能性有","place":["愛知県"],"place_en":["Aichi"],"genre":"人文学","institution":"東海中学校・高等学校","title":"専門学校・小中高等の教員相当","id":"D115020044","data":{"データ番号":"D115020044","公開開始日":"2015年02月03日","更新日":"2015年02月03日","求人件名":"東海中学校・高等学校 音楽科 非常勤講師募集","機関名":"東海中学校・高等学校","機関種別":"その他教育機関","求人内容":"<div class=\"margin-01\"><p style=\"word-wrap: break-word;\">[機関の説明(募集の背景、機関の詳細、プロジェクトの説明等)]<br><br><br>[仕事内容(業務内容、担当科目等)]<br>東海中学校・高等学校での、音楽の授業を行う。<br><br>[勤務地住所等]<br>名古屋市東区筒井1-2-35<br><br>[募集人員]<br>1名<br><br>[着任時期]<br>平成27年4月1日<br></p></div>","研究分野":"人文学","            小分類":"芸術学","職種":"\r\n            \r\n            専門学校・小中高等の教員相当\r\n            \r\n            ","":"専門学校・小中高等の教員相当","勤務形態":"非常勤（任期あり）","勤務地":"東海 -,愛知県","応募資格":"中学校及び高等学校教育職員免許状取得者。あるいは、平成27年3月末日までに取得見込みの者。","待遇":"持ち時間　　　９時間程度を予定　　　出校の曜日は相談による休日　　　日曜日、国民の祝日に関する法律に定める休日　　　年末年始、他に学園が必要と認めた日待遇　　　当学園の規定による　　　賞与有","募集期間":"2015年02月19日 必着,終了日前に採用者を決定する可能性有","応募・選考・結果通知・連絡先":"[応募方法(書類送付先も含む)]下の書類を簡易書留で郵送のこと。(1)履歴書　　写真添付、市販の用紙を利用、自筆に限る(2)中学校・高等学校教育職員免許状写し　　または免許状取得見込み証明書(3)教員免許更新による更新講習終了確認等の証明書写し　　(更新講習受講対象者のみ）(4)送付先　　住所：〒461-0003　　　　　名古屋市東区筒井1-2-35　　宛先：東海高等学校　　　　　教頭　佐藤泰年　※応募書類は返却いたしません。ご了承下さい。[選考内容(選考方法、採否の決定)、結果通知方法]　　書類審査結果は、メールまたは電話により連絡します。　その後、面接を行います。[連絡先(担当者所属、役職、氏名、e-mail、電話番号)] ※重要東海高等学校教頭　佐藤泰年電話：052-936-5111（代表）e-mail: tai-sato@tokai-jh.ed.jp","Web応募":"不可"}}