{"time":"2014-12-03 00:00:00 -0800","subject":"実験補助員募集（組織工学・再生医工学分野）","period":"2014-12-02:2015-01-31:適任者が決定次第、募集受付を早期終了する場合があります。","place":["東京都 神奈川県"],"place_en":[null],"genre":"複合領域:生物学","institution":"慶應義塾大学","title":"研究・教育補助者相当","id":"D114120072","data":{"データ番号":"D114120072","公開開始日":"2014年12月03日","更新日":"2014年12月03日","求人件名":"実験補助員募集（組織工学・再生医工学分野）","機関名":"慶應義塾大学","機関または部署":"http://www.sudo.sd.keio.ac.jp","部署名":"理工学部システムデザイン工学科生体医工学研究室","機関種別":"私立大学","求人内容":"<div class=\"margin-01\">[機関の説明(募集の背景、機関の詳細、プロジェクトの説明等)]<br>当研究室では肝臓や血管の組織工学・再生医工学の研究を進めています。その中で本学医学部との共同研究プロジェクトとして実験動物（ラット）の臓器（肝臓や腎臓）を利用した三次元培養の研究を計画しており、研究推進のためラットを用いた動物実験を行う実験補助員を募集致します。<br><br>[仕事内容(業務内容、担当科目等)]<br>ラットの肝臓や腎臓を摘出し、細胞を除外した臓器（脱細胞化臓器）を作製します。その他、細胞培養や簡単な事務作業（データ整理、研究室管理補助など）を行っていただきます。動物実験に関しては、サポートして技術を身につけていただきます。<br><br>[勤務地住所等]<br>慶應義塾大学理工学部キャンパス（神奈川県横浜市港北区日吉3-14-1）<br>※医学部キャンパス（東京都新宿区信濃町35）にて作業してもらうこともあります。<br><br>[募集人員]<br>1名<br><br>[着任時期]<br>2015年1月以降<br>,</div>","研究分野":"複合領域:生物学","            小分類":"基礎生物学","職種":"\r\n            \r\n            研究・教育補助者相当\r\n            \r\n            ","":"研究・教育補助者相当","勤務形態":"非常勤（任期あり）","勤務地":"関東 -,東京都 神奈川県","応募資格":"理工学系、生物系などの大学卒業または同程度の経験を持つ方。ラットを用いた動物実験が行える方。細胞培養の経験があることが望ましい。","待遇":"勤務時間　１日7時間程度 週3～5日（勤務日、時間は個別相談可） 時給は慶應義塾の規定に従う。","募集期間":"2014年12月02日 ～,2015年01月31日 必着,適任者が決定次第、募集受付を早期終了する場合があります。","応募・選考・結果通知・連絡先":"[応募方法(書類送付先も含む)]（１）履歴書（書式自由、写真貼付、email連絡先を明記） （２）これまでの業務経験等の詳細上記の書類をメールに添付して以下の連絡先まで応募してください。 [選考内容(選考方法、採否の決定)、結果通知方法]書類選考後、面接を行います。面接の日程は書類審査合格者に個別に連絡致します。[連絡先(担当者所属、役職、氏名、e-mail、電話番号)] ※重要慶應義塾大学理工学部システムデザイン工学科准教授 須藤 亮E-mail: sudo@sd.keio.ac.jp","Web応募":"可","機関紹介サイト":"当該機関の外部サイト情報を新規ウィンドウで表示します。"}}