{"time":"2014-10-25 00:00:00 -0700","subject":"研究補助員の募集（代謝内分泌病態内科学教室）","period":"NA:2014-12-25:NA","place":["大阪府"],"place_en":["Osaka"],"genre":"医歯薬学:医歯薬学","institution":"大阪市立大学","title":"研究・教育補助者相当","id":"D114101873","data":{"データ番号":"D114101873","公開開始日":"2014年10月25日","更新日":"2014年10月25日","求人件名":"研究補助員の募集（代謝内分泌病態内科学教室）","機関名":"大阪市立大学","機関または部署":"http://www.med.osaka-cu.ac.jp/interm2/","部署名":"大学院医学研究科　代謝内分泌病態内科学・老年血管病態学","機関種別":"公立大学","求人内容":"<div class=\"margin-01\">[機関の説明(募集の背景、機関の詳細、プロジェクトの説明等)]<br>大阪市立大学大学院医学研究科・代謝内分泌病態内科学教室では糖尿病・肥満・慢性腎臓病・動脈硬化症に関する基礎・応用研究の補助に従事する研究補助員を募集します。<br><br>[業務内容]<br>動物実験 (マウス、ラット等)、細胞培養、免疫染色、核酸・蛋白質の解析等生化学実験の補助、研究室の管理<br><br>[勤務地住所等]<br>大阪市立大学大学院医学研究科代謝内分泌病態内科学・老年血管病態学研究室<br>〒545-8585 大阪市阿倍野区旭町1-4-3<br><br>[募集人員]<br>　１名<br><br>[着任時期]<br>　2015年1月<br>,</div>","研究分野":"医歯薬学:医歯薬学","            小分類":"基礎医学","職種":"\r\n            \r\n            研究・教育補助者相当\r\n            \r\n            ","":"研究・教育補助者相当","勤務形態":"非常勤（任期あり）,年度ごとに更新、その場合でも最長５年","勤務地":"近畿 -,大阪府","応募資格":"理系（生物系）大学、短大もしくは専門学校卒、またはそれに準じる方。経験のある方を優先いたします。","待遇":"[職名]研究補助員[給与]本学給与規定による（時給1,500円～)、交通費支給、有給休暇あり[勤務時間]月曜から金曜まで、10時から17時 (応相談)、休日：土日祝日[社会保険]健康保険、厚生年金保険、雇用保険、労災保険","募集期間":"2014年12月25日 必着","応募・選考・結果通知・連絡先":"[応募方法]履歴書（写真添付）を下記連絡先までＥメールでお送り下さい（経歴、実験スキル等についても記載して下さい）。応募書類は返却いたしませんので予めご了承ください。[連絡先]〒545-8585 大阪市阿倍野区旭町1-4-3　大阪市立大学大学院医学研究科　代謝内分泌病態内科学担当：塩井　淳　TEL:06-6645-3806 E-mail:as@med.osaka-cu.ac.jp[選考方法]書類選考の上、面接日を連絡いたします。","Web応募":"不可"}}