{"time":"2015-04-24 00:00:00 +0900","subject":"准教授公募（名古屋大学大学院多元数理科学研究科）","period":"2015-03-16:2015-05-15:NA","place":["愛知県"],"place_en":["Aichi"],"genre":"数物系科学","institution":"名古屋大学","title":"准教授・常勤専任講師相当","id":"D115041003","data":{"データ番号":"D115041003","公開開始日":"2015年04月24日","更新日":"2015年04月24日","求人件名":"准教授公募（名古屋大学大学院多元数理科学研究科）","機関名":"名古屋大学","機関または部署":"http://www.math.nagoya-u.ac.jp","部署名":"大学院多元数理科学研究科","機関種別":"国立大学","公募の":"http://www.math.nagoya-u.ac.jp/ja/job","求人内容":"<div class=\"margin-01\"><p style=\"word-wrap: break-word;\">[機関の説明(募集の背景、機関の詳細、プロジェクトの説明等)]<br><br>職種: 准教授<br>研究分野:確率論とその関連分野<br><br>[仕事内容(業務内容、担当科目等)]<br>教育・運営<br><br>[勤務地住所等]<br>〒464-8602<br>名古屋市千種区不老町<br><br>[募集人員]<br>1名<br><br>[着任時期]<br>2015年10月1日以降なるべく早く</p></div>","研究分野":"数物系科学","            小分類":"数学","職種":"\r\n            \r\n            准教授・常勤専任講師相当\r\n            \r\n            ","":"准教授・常勤専任講師相当","勤務形態":"常勤（任期なし）","勤務地":"東海 -,愛知県","応募資格":"http://www.math.nagoya-u.ac.jp/ja/jobをご参照ください．","待遇":"准教授として採用．","募集期間":"2015年03月16日 ～,2015年05月15日 必着","応募・選考・結果通知・連絡先":"[応募方法(書類送付先も含む)]http://www.math.nagoya-u.ac.jp/ja/jobをご参照ください．[選考内容(選考方法、採否の決定)、結果通知方法]http://www.math.nagoya-u.ac.jp/ja/jobをご参照ください．[連絡先(担当者所属、役職、氏名、e-mail、電話番号)] ※重要名古屋大学大学院多元数理科学研究科准教授選考委員会委員長吉田伸生ap-search-2015-a@math.nagoya-u.ac.jp052 789 2420","Web応募":"不可","機関紹介サイト":"当該機関の外部サイト情報を新規ウィンドウで表示します。"}}