{"time":"2014-07-28 00:00:00 -0700","subject":"信州大学学術研究院工学系 教授（主担当：工学部機械システム工学科）公募","period":"NA:2014-11-14:NA","place":"北陸・甲信越 -,長野県","place_en":"Nagano","genre":"工学:工学","institution":"信州大学","title":"教授相当","id":"D114071479","data":{"データ番号":"D114071479","公開開始日":"2014年07月26日","更新日":"2014年07月28日","求人件名":"信州大学学術研究院工学系 教授（主担当：工学部機械システム工学科）公募","機関名":"信州大学","機関または部署":"http://www.mech.shinshu-u.ac.jp/","部署名":"学術研究院 工学系　機械システム工学科","機関種別":"国立大学","公募の":"http://www.mech.shinshu-u.ac.jp/2014/07/15321.html","求人内容":"<div class=\"margin-01\">[機関の説明(募集の背景、機関の詳細、プロジェクトの説明等)]<br>地球環境問題の顕在化，グリーンテクノロジー，自然エネルギー、水問題等への社会の関心の高まりに伴い，これらの諸問題に対し機械工学に基づく技術を適用して問題解決を図ることができる技術者の育成が望まれている。そのためには，学部および大学院での基礎科目である熱力学の習得は必須であり，それに基づく教育・研究は今後ますます重要になると考えられる。しかしながら，これらの関連科目を教育・研究できる教員は現時点で欠いているため，当該分野を専門とした教授を一般公募により募集する。<br><br>[仕事内容(業務内容、担当科目等)]<br>・熱流体システム工学分野（熱工学，伝熱工学，相変化，熱・物質移動，エネルギー工学，燃焼工学など）に関する研究<br>・熱力学，伝熱工学，エネルギー変換工学などの授業・演習，関連する大学院の専門科目を担当<br><br><br>[勤務地住所等]<br>〒380-8553　長野県長野市若里4-17-1<br><br>[募集人員]<br>1名<br>教授<br><br>[着任時期]<br>2015年04月01日<br><br>,</div>","研究分野":"工学:工学","            小分類":"総合工学","職種":"\r\n            \r\n            教授相当\r\n            \r\n            ","":"教授相当","勤務形態":"常勤（任期なし）","勤務地":"北陸・甲信越 -,長野県","応募資格":"博士の学位を有していること","待遇":"国立大学法人信州大学の規定に基づく定年　：65才 退職日：定年に達した日以後における最初の3月31日","募集期間":"2014年11月14日 必着,必着","応募・選考・結果通知・連絡先":"[応募方法(書類送付先も含む)]【提出書類】（1）履歴書（任意書式，ワープロ可，写真貼付，e-mailアドレス記入）（2）研究業績リスト（著書，学術論文，国際会議論文，解説，学会口頭発表，特許などに区別し，共著者はすべて記入すること）（3）科研費などの研究費取得実績と受賞歴（4）主要論文5編の別刷りまたはコピー（5）教育と研究に対する抱負（A4用紙１枚程度）※(2)および(3)については、書式と記載例を学科ホームページに掲載していますので、ダウンロードして使用してください。【書類の送付先】〒380-8553　長野県長野市若里4-17-1信州大学 工学部長　大石　修治　宛（封筒に「機械システム工学科 教授（熱流体システム工学教育分野）応募書類在中」と朱書きの上，簡易書留にて郵送下さい。なお，提出書類は選考終了後も返却いたしませんが，採用選考以外の目的で使用することはありませんので，ご了承下さい。）[選考内容(選考方法、採否の決定)、結果通知方法]一次選考：書類審査，二次選考：面接審査（2014年12月下旬に実施予定）[連絡先(担当者所属、役職、氏名、e-mail、電話番号)] ※重要信州大学工学部機械システム工学科　学科長　吉野 正人電話：026-269-5116  Fax：026-269-5116E-mail: masato@shinshu-u.ac.jp","添付書類":"1.form2(2)(3).doc","備考":"信州大学は男女共同参画を推進しており，業績等（研究業績，教育業績，社会的貢献ほか）及び人物の評価において同等と認められた場合には女性を採用します。ただし，これは性別のみで優先的に採用することを認めるものではありません。","Web応募":"不可"}}