{"time":"2014-12-02 00:00:00 -0800","subject":"講師の公募（薬局薬学研究室）","period":"NA:2015-01-30:NA","place":["岐阜県"],"place_en":["Gifu"],"genre":"医歯薬学","institution":"岐阜薬科大学","title":"准教授・常勤専任講師相当","id":"D114120017","data":{"データ番号":"D114120017","公開開始日":"2014年12月02日","更新日":"2014年12月02日","求人件名":"講師の公募（薬局薬学研究室）","機関名":"岐阜薬科大学","機関または部署":"http://www.gifu-pu.ac.jp/","機関種別":"公立大学","求人内容":"<div class=\"margin-01\">本学では下記の通り教員を募集します。<br><br>職名及び人員<br>　講師　１名<br><br>担当研究室<br>　実践薬学大講座 薬局薬学研究室<br><br>主な職務内容<br>　(1) 実務：岐阜薬科大学付属薬局における薬剤業務<br>　(2) 教育：薬学生の実務教育及び研究指導<br><br>任用予定日<br>　平成27年4月1日を予定（委細面談）<br><br>勤務地<br>　岐阜市大学西1丁目108の3<br>　岐阜薬科大学付属薬局<br>,</div>","研究分野":"医歯薬学","            小分類":"薬学","職種":"\r\n            \r\n            准教授・常勤専任講師相当\r\n            \r\n            ","":"准教授・常勤専任講師相当","勤務形態":"常勤（任期あり）,５年の任期制（再任可）","勤務地":"東海 -,岐阜県","応募資格":"本学教員選考規程（ホームページ参照）に該当し、かつ以下の条件を有する方　(1) 薬剤師の資格を有する者　(2) 学部教育並びに大学院における研究指導に積極的に取り組める者　(3) 修士修了又は６年制薬学教育卒業以上が望ましい　(4) 岐阜市内又はその近郊に居住できること","待遇":"職名　岐阜市公立学校教員（大学教員）給与　学歴・職歴により決定勤務時間　岐阜市職員の勤務時間、休暇等に関する条例　　　　　岐阜市職員の勤務時間、休暇等に関する規則等参照休日　同上保険（共済）　公立学校共済組合岐阜支部に加入　　　","募集期間":"2015年01月30日 必着","応募・選考・結果通知・連絡先":"提出書類　(1) 履歴書　　　　　　　　　　　　１通（書式参照）　(2) 主要研究業績の概要　　　　　　１通（書式参照）　(3) 教育の抱負と研究計画　　　　　１通（書式参照）　(4) 最終学歴の卒業又は修了証明書　１通　(5) 薬剤師免許証の写し　　　　　　１通＊提出された書類は、個人情報保護法に基づいて適切に取扱い、返却いたしません。＊提出書類の書式（電子ファイル）は、ホームページ（下記）からダウンロードしてください。＊書類選考後、候補者に対する面談などを行うことがあります。＊封筒に「公募書類在中」と朱書きし、簡易書留で郵送してください。提出先　〒501-1196　岐阜市大学西1丁目25番地4　岐阜薬科大学　事務局気付　　薬局薬学研究室教員選考委員会　　　TEL：058-230-8100　　　FAX：058-230-8200　　　ホームページ　http://www.gifu-pu.ac.jp問合せ先　〒501-1113　岐阜市大学西1丁目108番地3　岐阜薬科大学付属薬局　　寺町　ひとみ　　　TEL：058-293-0220　　　FAX：058-293-0221　　　E-mail:teramachih@gifu-pu.ac.jp","Web応募":"不可"}}