{"time":"2014-10-29 00:00:00 -0700","subject":"医学教育開発研究センター(MEDC)助教の公募について","period":"2014-10-29:2014-12-26:NA","place":["岐阜県"],"place_en":["Gifu"],"genre":"医歯薬学","institution":"岐阜大学","title":"助教相当","id":"D114102027","data":{"データ番号":"D114102027","公開開始日":"2014年10月29日","更新日":"2014年10月29日","求人件名":"医学教育開発研究センター(MEDC)助教の公募について","機関名":"岐阜大学","機関または部署":"http://www1.gifu-u.ac.jp/~medc/","部署名":"医学教育開発研究センター","機関種別":"国立大学","求人内容":"<div class=\"margin-01\">[機関の説明(募集の背景、機関の詳細、プロジェクトの説明等)]<br><br><br>[仕事内容(業務内容、担当科目等)]<br>医学教育開発研究センターの教育・研究業務<br>（１）卒前・卒後の医学教育<br>（２）医学教育セミナーとワークショップ<br>（３）医学教育に関する研究<br>（４）その他の共同利用拠点としての事業<br><br><br><br>[勤務地住所等]<br><br><br>[募集人員]<br>1名<br>特任助教<br><br>[着任時期]<br>平成27年4月1日以降<br><br>,</div>","研究分野":"医歯薬学","            小分類":"医学教育","職種":"\r\n            \r\n            助教相当\r\n            \r\n            ","":"助教相当","勤務形態":"常勤（任期あり）,1年ごとの更新（終了：平成32年3月予定）","勤務地":"東海 -,岐阜県","応募資格":"特になし。","待遇":"給与、通勤手当、有給休暇等の待遇は岐阜大学の規定による。※給与は年俸制とする。","募集期間":"2014年10月29日 ～,2014年12月26日 必着","応募・選考・結果通知・連絡先":"[応募方法(書類送付先も含む)]提出書類 ：（１）履歴書（指定様式）（２）業績一覧表（指定様式）提出期限 ： 平成２６年１２月２６日（金）（必着）　　封筒には「医学教育開発研究センター助教応募書類在中」と朱書し，書留で郵送願います。提出先等 ： 〒501-1194　岐阜市柳戸１番１　岐阜大学医学教育開発研究センター　センター長　宛[選考内容(選考方法、採否の決定)、結果通知方法][連絡先(担当者所属、役職、氏名、e-mail、電話番号)] ※重要〒501-1194岐阜県 岐阜市柳戸１番１岐阜大学医学教育開発研究センター 事務室E-mail:gjme00028@jim.gifu-u.ac.jpTEL:058-230-6470FAX:058-230-6468","添付書類":"1.1  履歴書（医）.xls,2.2  業績一覧表.doc","Web応募":"不可"}}