{"time":"2014-11-08 00:00:00 -0800","subject":"研究員募集（法政大学マイクロ・ナノテクノロジー研究センター）","period":"NA:2015-01-10:適任者が決まり次第締め切ります。","place":["東京都"],"place_en":["Tokyo"],"genre":"生物学:総合理工:複合領域","institution":"法政大学","title":"研究員・ポスドク相当","id":"D114110220","data":{"データ番号":"D114110220","公開開始日":"2014年11月08日","更新日":"2014年11月08日","求人件名":"研究員募集（法政大学マイクロ・ナノテクノロジー研究センター）","機関名":"法政大学","機関または部署":"http://www.hosei.ac.jp/seimei/index.html","部署名":"生命科学部","機関種別":"私立大学","求人内容":"<div class=\"margin-01\">[機関の説明(募集の背景、機関の詳細、プロジェクトの説明等)]<br>法政大学マイクロ・ナノテクノロジー研究センターが推進するプロジェクト「グリーンテクノロジーを支える次世代エネルギー変換システム」に参画する研究員を募集します。<br><br>[仕事内容(業務内容)]<br>生物物理学（特にナノ計測、蛍光イメージング）、分子生物学、生化学等を組み合わせ、生物分子モーターがもつ高効率エネルギー変換機構の解明を目指す研究プロジェクトを推進していただきます。また、プロジェクト内の異分野研究にも積極的に興味をもち、共同研究を進めてくださる方を希望します。<br><br>[勤務地住所等]<br>東京都小金井市梶野町3-7-2　および　東京都小金井市緑町3-11-15（小金井キャンパス緑町校舎内）<br>JR中央線　東小金井駅より徒歩15分程度<br><br>[募集人員]<br>1名<br><br>[着任時期]<br>2015年4月1日</div>","研究分野":"生物学:総合理工:複合領域","            小分類":"生体分子科学","職種":"\r\n            \r\n            研究員・ポスドク相当\r\n            \r\n            ","":"研究員・ポスドク相当","勤務形態":"常勤（任期あり）,任期： 1年，単年度契約の更新により，最長2018年3月末まで","勤務地":"関東 -,東京都","応募資格":"1) 博士の学位を有するか、2015年3月末までに取得見込みであること。2) 生物物理学、分子生物学、生化学などの生命科学研究分野における経験・実績を有し、上記研究内容に意欲的に取り組んでいただけること。","待遇":"給与月額：375,000円通勤費：有（当大学規程による）その他：手当、賞与、退職金等は支給しない休日：土日、祝日、年末年始及び勤務日の指定をしない日健康保険、厚生年金、雇用保険：加入","募集期間":"2015年01月10日 必着,適任者が決まり次第締め切ります。","応募・選考・結果通知・連絡先":"[応募方法(書類送付先も含む)]1）履歴書（写真貼付、電話番号・E-mail明記）2）業績一覧（原著論文、総説、特許、学会発表等）3）これまでの研究概要(A4用紙1~2枚程度)4）応募者の所見を求めうる方２名の氏名、所属、応募者との関係、連絡先（電話、E-mail）を「PD応募書類在中」と封筒に朱書きして、下記連絡先宛に郵送してください。※応募書類は返却致しませんのでご了承ください。※質問等は件名に「PD応募」と明記し、下記E-mailにお問い合せください。[選考内容(選考方法、採否の決定)、結果通知方法]書類選考を行ったのち、対象者に連絡して面接選考を行います。[連絡先(担当者所属、役職、氏名、e-mail、電話番号)] ※重要書類送付先：〒184-8584　東京都小金井市梶野町3-7-2　法政大学生命科学部　曽和義幸　宛E-mail: ysowa@（@以下に hosei.ac.jp をつけてください）","Web応募":"不可"}}