{"time":"2014-12-12 00:00:00 -0800","subject":"情報理工学部　助手　募集","period":"NA:2015-01-09:NA","place":["滋賀県"],"place_en":["Shiga"],"genre":"情報学","institution":"立命館大学","title":"研究・教育補助者相当","id":"D114120700","data":{"データ番号":"D114120700","公開開始日":"2014年12月12日","更新日":"2014年12月12日","求人件名":"情報理工学部　助手　募集","機関名":"立命館大学","機関または部署":"http://www.ritsumei.ac.jp/ise/","部署名":"情報理工学部","機関種別":"私立大学","公募の":"http://www.ritsumei.jp/job/index_j.html","求人内容":"<div class=\"margin-01\">【任用職名】　助手<br>【募集人数】　若干名<br>【所　　属】　情報理工学部<br>【研究分野】　情報コミュニケーション分野、情報システム分野、メディア情報分野、知能情報分野<br>【業務内容】　教育研究の補助を行うことを主たる職務の基本とし、具体的な職務内容は下記の通りとする。<br>①実験・実習系科目等の補助業務（標準10 授業時間*：前期20 時間、後期20 時間）*１授業時間は2 時間<br>②研究室における学生の日常的な研究指導補助業務<br>③定期試験監督業務（前期10 回、後期10 回）<br>④その他、所属長が指示する業務<br>⑤上記業務以外に、勤務する学部・学科の承認を得て、その監督下で専攻分野の研究に従事することができる。<br>【勤務地住所等】<br>〒525-8577<br>滋賀県草津市野路東1丁目1-1<br>【着任時期】　2015年4月1日<br><br>,</div>","研究分野":"情報学","            小分類":"全て","職種":"\r\n            \r\n            研究・教育補助者相当\r\n            \r\n            ","":"研究・教育補助者相当","勤務形態":"常勤（任期あり）,【任期】2015年4月1日～2020年3月31日（再任不可）＊ 但し、双方合意の場合1年毎の契約により、4回を上限として契約を更新する。","勤務地":"近畿 -,滋賀県","応募資格":"【応募資格】修士学位（専門職学位を含む）を有する者、または同等以上の能力を有する者。＊上記資格を満たしても、2015年4月1日現在、学生の身分を有する者は応募できない。","待遇":"【給与等】本俸 3,750,000円（税込み）＊通勤手当等の諸手当等は、規程に基づき支給する。","募集期間":"2015年01月09日 必着","応募・選考・結果通知・連絡先":"【提出書類】①履歴書・業績書【本学所定様式】②研究業績書【様式A】③最終学位の学位論文の論題とその概要【所定用紙（A4版）】④教育・研究に関する抱負【所定用紙A4版】※①～④の書式は本学ホームページよりダウンロードしてご使用下さい。http://www.ritsumei.jp/job/index_j.html⑤最終学歴修了（卒業）証明書（修了見込みの場合は、そのことを証明するものが必要）※上記提出書類は、紙媒体のものと共に、電子媒体（CD-RあるいはDVD-R）に格納したものをお送りください。電子媒体には、①のワードファイル、②のエクセルファイル、③～⑤それぞれのPDF を格納してください。提出書類は返却しませんので、予めご了承ください。なお、応募においてご提供いただいた個人情報は、本学の規程に従って適切に管理し、採用選考以外の目的には使用いたしません。【書類提出先】　〒525-8577 滋賀県草津市野路東1丁目1－1立命館大学情報理工学部事務室「助手」採用係※「助手応募書類在中」と朱書きで明記し、必ず書留にて郵送してください。【選考方法】①書類選考②面接","備考":"【問合せ先】　立命館大学情報理工学部事務室（担当：橋本・成瀬）TEL: 077-561-5202 FAX：077-561-5203E-mail：johokobo@st.ritsumei.ac.jp","Web応募":"不可"}}